Workbook

Sheet Assessment
A1: Capacidad | B1: Subcapacidad | C1: Objetivo de evaluación | D1: Nivel 1 - Inicial | E1: Nivel 2 - Estructurado | F1: Nivel 3 - Estandarizado | G1: Nivel 4 - Optimizado | H1: Nivel 5 - Avanzado/Referente | I1: Casos de uso AI asociados | J1: Score Procesos | K1: Score Tecnología | L1: Score Organización | M1: Score Medio | N1: Nivel resultante | O1: Gap vs objetivo | P1: Prioridad | Q1: Preguntas clave | R1: Evidencias | S1: Iniciativa sugerida | T1: Comentarios / hallazgos
A2: Control y tratamiento contable | B2: 1.1 Gobierno del tratamiento contable de operaciones de tesorería | C2: Evaluar si las operaciones de tesorería tienen un tratamiento contable gobernado, trazable y coordinado con cierre contable y reporting. | D2: Registro contable de operaciones de tesorería manual, reactivo y con baja trazabilidad de criterios y aprobaciones. | E2: Criterios contables básicos definidos para operaciones relevantes, aunque con revisiones manuales y variabilidad entre entidades. | F2: Políticas documentadas para tratamiento contable de instrumentos, intereses, comisiones y ajustes de tesorería. | G2: Proceso integrado con cierre contable, reporting y controles automáticos, con revisión periódica de criterios y excepciones. | H2: Modelo basado en IA que detecta tratamientos anómalos, sugiere clasificaciones contables y explica variaciones de resultados financieros. | I2: Detección de asientos inusuales en el cierre; Detección de inconsistencias en datos maestros; Análisis de desviaciones con explicación automática | M2: =IF(COUNT(J2:L2)=0,"",ROUND(AVERAGE(J2:L2),0)) | N2: =IF(M2="","",CHOOSE(M2,"1 - Inicial","2 - Estructurado","3 - Estandarizado","4 - Optimizado","5 - Avanzado/Referente")) | O2: =IF(M2="","",MAX(0,4-M2)) | P2: =IF(O2="","",IF(O2>=3,"Alta",IF(O2=2,"Media",IF(O2=1,"Media","Baja")))) | Q2: ¿Existen políticas contables para operaciones de tesorería? ¿Se revisa el tratamiento contable de instrumentos, intereses y comisiones? ¿Se conectan con cierre y reporting? ¿Hay trazabilidad de ajustes? | R2: Políticas contables; registros de operaciones; conciliaciones; evidencias de revisión; workpapers; reporting financiero. | S2: Definir gobierno del tratamiento contable de tesorería con políticas, controles, trazabilidad, responsables y revisión recurrente de excepciones.
A3: Control y tratamiento contable | B3: 1.2 Registro, conciliación y devengo de intereses y comisiones | C3: Evaluar la calidad del registro, devengo, conciliación y explicación de intereses, comisiones y gastos financieros. | D3: Devengos y registros manuales, con conciliaciones puntuales y dependencia de hojas de cálculo. | E3: Plantillas recurrentes para devengos y conciliaciones, aunque con controles manuales y baja automatización. | F3: Modelo estándar de devengos y conciliaciones con reglas, calendarios, fuentes, soportes y responsables definidos. | G3: Devengos integrados con contratos, bancos, deuda, cierre y reporting, con controles automáticos y explicación de variaciones. | H3: IA identifica devengos esperados, detecta omisiones o anomalías y genera explicaciones inteligentes de variaciones financieras. | I3: Detección de provisiones omitidas; Análisis de desviaciones con explicación automática; Conciliación a nivel de transacción | M3: =IF(COUNT(J3:L3)=0,"",ROUND(AVERAGE(J3:L3),0)) | N3: =IF(M3="","",CHOOSE(M3,"1 - Inicial","2 - Estructurado","3 - Estandarizado","4 - Optimizado","5 - Avanzado/Referente")) | O3: =IF(M3="","",MAX(0,4-M3)) | P3: =IF(O3="","",IF(O3>=3,"Alta",IF(O3=2,"Media",IF(O3=1,"Media","Baja")))) | Q3: ¿Se registran devengos de forma sistemática? ¿Se concilian intereses y comisiones con bancos/contratos? ¿Se explican variaciones? ¿Se detectan omisiones? | R3: Contratos financieros; extractos bancarios; cálculos de intereses; conciliaciones; asientos; reportes de variación; evidencias de aprobación. | S3: Implantar modelo de devengo y conciliación de intereses/comisiones con reglas, fuentes oficiales, controles y alertas de omisiones.
A4: Control y tratamiento contable | B4: 1.3 Calidad del dato maestro financiero y bancario | C4: Evaluar si los datos maestros financieros y bancarios son fiables, completos, actualizados y gobernados. | D4: Maestros bancarios y financieros gestionados manualmente, con duplicidades, inconsistencias y controles limitados. | E4: Controles básicos de actualización y validación, aunque con workflow parcial y visibilidad limitada de calidad del dato. | F4: Modelo de gobierno de datos maestros financieros con owners, reglas, aprobaciones, controles y auditoría de cambios. | G4: Gobierno integrado con bancos, ERP, TMS, pagos, deuda y reporting, con controles automáticos y gestión de incidencias. | H4: IA detecta inconsistencias en datos maestros, propone remediación y guía flujos de trabajo adaptativos de cambios financieros/bancarios. | I4: Detección de inconsistencias en datos maestros; Flujos guiados de cambio en datos maestros; Generación de documentación de metadatos | M4: =IF(COUNT(J4:L4)=0,"",ROUND(AVERAGE(J4:L4),0)) | N4: =IF(M4="","",CHOOSE(M4,"1 - Inicial","2 - Estructurado","3 - Estandarizado","4 - Optimizado","5 - Avanzado/Referente")) | O4: =IF(M4="","",MAX(0,4-M4)) | P4: =IF(O4="","",IF(O4>=3,"Alta",IF(O4=2,"Media",IF(O4=1,"Media","Baja")))) | Q4: ¿Existen owners de datos maestros bancarios? ¿Se controlan altas/cambios? ¿Hay auditoría de cambios? ¿Se mide calidad de dato? | R4: Maestros bancarios; workflows de alta/cambio; logs; controles de calidad; incidencias; aprobaciones; políticas de datos. | S4: Implantar gobierno de datos maestros financieros y bancarios con responsables, flujo de trabajo, controles automáticos, trazabilidad y gestión de incidencias.
A5: Control y tratamiento contable | B5: 1.4 Reporting financiero de resultados de tesorería | C5: Evaluar si los resultados financieros de tesorería se reportan de forma clara, oportuna y explicable para dirección y cierre. | D5: Reporting de resultados financieros manual, agregado y orientado al cierre, con baja explicación de drivers. | E5: Reporting recurrente de gastos/ingresos financieros, aunque con narrativa limitada y análisis manual. | F5: Reporting estándar con KPIs, variaciones, drivers, posiciones, coste financiero y comentarios ejecutivos. | G5: Reporting integrado con deuda, liquidez, inversiones, riesgos financieros, forecast y acciones de gestión. | H5: Informes basados en IA, con narrativa automática, explicación de los drivers, alertas tempranas y recomendaciones sobre coste financiero y liquidez. | I5: Visión ejecutiva de la salud financiera; Análisis de desviaciones con explicación automática; Analista digital de Finanzas bajo demanda | M5: =IF(COUNT(J5:L5)=0,"",ROUND(AVERAGE(J5:L5),0)) | N5: =IF(M5="","",CHOOSE(M5,"1 - Inicial","2 - Estructurado","3 - Estandarizado","4 - Optimizado","5 - Avanzado/Referente")) | O5: =IF(M5="","",MAX(0,4-M5)) | P5: =IF(O5="","",IF(O5>=3,"Alta",IF(O5=2,"Media",IF(O5=1,"Media","Baja")))) | Q5: ¿Se reportan resultados financieros de tesorería? ¿Se explican drivers de variación? ¿Se conectan con liquidez, deuda y riesgos? ¿Se generan acciones? | R5: Reporting de tesorería; análisis de variaciones; KPIs de coste financiero; comité financiero; forecast; acciones de gestión. | S5: Crear informes financieros de tesorería con drivers, KPIs, narrativa ejecutiva, conexión con la previsión y recomendaciones de acción.
A6: Gestión de riesgos financieros | B6: 2.1 Marco de gestión de riesgos financieros y políticas | C6: Evaluar si existe un marco formal para identificar, medir, limitar y gobernar riesgos financieros: FX, tipos, crédito, liquidez y contraparte. | D6: Riesgos financieros gestionados de forma reactiva, con políticas incompletas y límites poco formalizados. | E6: Políticas básicas y límites para riesgos principales, aunque con seguimiento manual y cobertura parcial. | F6: Marco de gestión de riesgos financieros documentado con apetito, límites, roles, métricas, aprobaciones y reporting. | G6: Gestión integrada con posiciones, exposiciones, coberturas, escenarios, límites y comités de seguimiento. | H6: Modelo basado en IA que monitoriza exposiciones, detecta desviaciones frente a límites y recomienda acciones de cobertura o mitigación. | I6: Optimización de operaciones de divisa; Agentes de IA para análisis de riesgo crediticio; Monitorización predictiva del cumplimiento | M6: =IF(COUNT(J6:L6)=0,"",ROUND(AVERAGE(J6:L6),0)) | N6: =IF(M6="","",CHOOSE(M6,"1 - Inicial","2 - Estructurado","3 - Estandarizado","4 - Optimizado","5 - Avanzado/Referente")) | O6: =IF(M6="","",MAX(0,4-M6)) | P6: =IF(O6="","",IF(O6>=3,"Alta",IF(O6=2,"Media",IF(O6=1,"Media","Baja")))) | Q6: ¿Existe política de riesgos financieros? ¿Se definen límites y apetito de riesgo? ¿Se monitorizan exposiciones? ¿Hay reporting a comité? | R6: Política de riesgos; límites; exposiciones; reportes de comité; aprobaciones; métricas VaR/sensibilidad; excepciones. | S6: Definir marco integral de riesgos financieros con políticas, límites, métricas, informes, gobierno y flujo de excepciones.
A7: Gestión de riesgos financieros | B7: 2.2 Medición y cobertura de riesgo de divisa | C7: Evaluar la capacidad para identificar, medir, forecastar y cubrir exposiciones de divisa de forma alineada con política y negocio. | D7: Exposición FX identificada parcialmente y gestionada mediante análisis manual o coberturas puntuales. | E7: Forecast de exposición y coberturas básicas, aunque con baja integración con presupuesto, ventas/compras o cash forecast. | F7: Modelo estándar de exposición FX con fuentes, periodicidad, sensibilidad, instrumentos, aprobaciones y reporting. | G7: Gestión integrada de FX con forecast, operaciones, posiciones, escenarios, límites, efectividad de cobertura y contabilidad. | H7: IA identifica patrones de tipo de cambio, anticipa exposición, simula escenarios y recomienda estrategias de cobertura según riesgo, coste y política. | I7: Optimización de operaciones de divisa; Generación de estrategias de inversión | M7: =IF(COUNT(J7:L7)=0,"",ROUND(AVERAGE(J7:L7),0)) | N7: =IF(M7="","",CHOOSE(M7,"1 - Inicial","2 - Estructurado","3 - Estandarizado","4 - Optimizado","5 - Avanzado/Referente")) | O7: =IF(M7="","",MAX(0,4-M7)) | P7: =IF(O7="","",IF(O7>=3,"Alta",IF(O7=2,"Media",IF(O7=1,"Media","Baja")))) | Q7: ¿Se mide exposición FX por moneda y horizonte? ¿Se conecta con forecast y operaciones? ¿Se evalúa efectividad de coberturas? ¿Se simulan escenarios? | R7: Mapa de exposición FX; forecast por moneda; contratos de cobertura; sensibilidad; hedge effectiveness; reporting de límites. | S7: Implantar modelo de gestión del riesgo de divisa con previsión de exposición, límites, escenarios, seguimiento de coberturas y recomendaciones de mitigación.
A8: Gestión de riesgos financieros | B8: 2.3 Gestión de riesgo de tipos, contraparte y crédito financiero | C8: Evaluar si la organización mide y gestiona riesgo de tipo de interés, contraparte, crédito financiero y exposición con entidades financieras. | D8: Riesgos de tipo, contraparte o crédito financiero gestionados de forma puntual, con visibilidad limitada de exposición consolidada. | E8: Seguimiento básico de deuda, tipos y contrapartes principales, aunque con análisis manual y límites parciales. | F8: Modelo definido de exposición a tipos/contrapartes con métricas, límites, ratings, sensibilidad y políticas de diversificación. | G8: Gestión integrada con deuda, inversiones, bancos, derivados, límites, escenarios macro y decisiones de financiación/inversión. | H8: IA calcula sensibilidades, anticipa cambios de riesgo, alerta sobre límites y recomienda acciones de refinanciación, cobertura o diversificación. | I8: Agentes de IA para análisis de riesgo crediticio; Valoración predictiva de la compañía | M8: =IF(COUNT(J8:L8)=0,"",ROUND(AVERAGE(J8:L8),0)) | N8: =IF(M8="","",CHOOSE(M8,"1 - Inicial","2 - Estructurado","3 - Estandarizado","4 - Optimizado","5 - Avanzado/Referente")) | O8: =IF(M8="","",MAX(0,4-M8)) | P8: =IF(O8="","",IF(O8>=3,"Alta",IF(O8=2,"Media",IF(O8=1,"Media","Baja")))) | Q8: ¿Se mide sensibilidad a tipos? ¿Existen límites por contraparte? ¿Se monitorizan ratings y concentración? ¿Se conectan riesgos con deuda/inversiones? | R8: Mapa de contrapartes; ratings; límites; sensibilidad a tipos; cartera de deuda; derivados; reportes de concentración. | S8: Diseñar modelo de gestión de riesgo de tipos y contraparte con límites, sensibilidad, escenarios, alertas y decisiones de cobertura/diversificación.
A9: Gestión de riesgos financieros | B9: 2.4 Escenarios, stress testing y reporting de riesgos financieros | C9: Evaluar si Tesorería realiza escenarios y stress tests para anticipar impactos financieros y tomar decisiones preventivas. | D9: Escenarios financieros puntuales o cualitativos, con baja conexión con decisiones de liquidez, deuda o cobertura. | E9: Stress testing básico para riesgos relevantes, con supuestos manuales y reporting limitado. | F9: Metodología de escenarios financieros con variables, supuestos, sensibilidad, impactos y revisión periódica. | G9: Stress testing integrado con cash forecast, deuda, covenants, FX, tipos, liquidez, capital allocation y comités. | H9: IA simula escenarios dinámicos, identifica alertas tempranas, estima impactos y recomienda respuestas financieras preventivas. | I9: Previsión predictiva de flujo de caja; Optimización de operaciones de divisa; Patrones históricos para predecir el rendimiento | M9: =IF(COUNT(J9:L9)=0,"",ROUND(AVERAGE(J9:L9),0)) | N9: =IF(M9="","",CHOOSE(M9,"1 - Inicial","2 - Estructurado","3 - Estandarizado","4 - Optimizado","5 - Avanzado/Referente")) | O9: =IF(M9="","",MAX(0,4-M9)) | P9: =IF(O9="","",IF(O9>=3,"Alta",IF(O9=2,"Media",IF(O9=1,"Media","Baja")))) | Q9: ¿Se realizan stress tests financieros? ¿Se cuantifican impactos en liquidez/deuda/covenants? ¿Se conectan con decisiones de cobertura? ¿Hay alertas tempranas? | R9: Modelos de escenarios; supuestos macro; sensibilidad; reportes de stress; actas de comité; decisiones preventivas. | S9: Crear marco de pruebas de estrés financieras con variables clave, impactos, alertas y planes de respuesta.
A10: Mercados de deuda y capitales | B10: 3.1 Estrategia de financiación y estructura de capital | C10: Evaluar si existe una estrategia de financiación alineada con estructura de capital, liquidez, coste, riesgo y objetivos corporativos. | D10: Financiación gestionada de forma reactiva ante necesidades puntuales, con baja planificación de estructura de capital. | E10: Plan de financiación básico con análisis de deuda existente y necesidades previsibles, aunque con escenarios limitados. | F10: Estrategia de financiación definida con objetivos de estructura de capital, coste, vencimientos, liquidez, covenants y rating. | G10: Estrategia integrada con plan estratégico, cash forecast, inversiones, mercado, riesgos financieros y capital allocation. | H10: IA recomienda estrategias de financiación considerando mercado, coste de capital, rating, liquidez, escenarios y objetivos corporativos. | I10: Generación de estrategias de inversión; Valoración predictiva de la compañía; Visión ejecutiva de la salud financiera | M10: =IF(COUNT(J10:L10)=0,"",ROUND(AVERAGE(J10:L10),0)) | N10: =IF(M10="","",CHOOSE(M10,"1 - Inicial","2 - Estructurado","3 - Estandarizado","4 - Optimizado","5 - Avanzado/Referente")) | O10: =IF(M10="","",MAX(0,4-M10)) | P10: =IF(O10="","",IF(O10>=3,"Alta",IF(O10=2,"Media",IF(O10=1,"Media","Baja")))) | Q10: ¿Existe estrategia de financiación? ¿Se define estructura objetivo de capital? ¿Se analizan vencimientos y coste? ¿Se incorpora mercado y rating? | R10: Plan de financiación; estructura de capital; vencimientos; coste de deuda; rating/covenants; actas de comité; escenarios. | S10: Definir estrategia de financiación y estructura de capital con escenarios, vencimientos, coste, covenants, rating y conexión con plan estratégico.
A11: Mercados de deuda y capitales | B11: 3.2 Gestión de deuda, covenants y relación con financiadores | C11: Evaluar la gestión operativa y estratégica de deuda, covenants, financiación bancaria y relación con entidades financieras. | D11: Deuda y covenants gestionados manualmente, con seguimiento disperso y baja anticipación de riesgos de incumplimiento. | E11: Seguimiento básico de deuda, amortizaciones y covenants, aunque con reporting manual y documentación dispersa. | F11: Modelo estándar de gestión de deuda con calendario, contratos, covenants, costes, responsables y reporting periódico. | G11: Gestión integrada en TMS/ERP con alertas, escenarios, covenant forecasting, relación bancaria y control de documentación. | H11: IA anticipa riesgos de covenant, recomienda acciones de refinanciación y sintetiza documentación financiera para financiadores. | I11: Visión ejecutiva de la salud financiera; Previsión predictiva de flujo de caja; Informes de investigación y KYC | M11: =IF(COUNT(J11:L11)=0,"",ROUND(AVERAGE(J11:L11),0)) | N11: =IF(M11="","",CHOOSE(M11,"1 - Inicial","2 - Estructurado","3 - Estandarizado","4 - Optimizado","5 - Avanzado/Referente")) | O11: =IF(M11="","",MAX(0,4-M11)) | P11: =IF(O11="","",IF(O11>=3,"Alta",IF(O11=2,"Media",IF(O11=1,"Media","Baja")))) | Q11: ¿Se monitorizan covenants y vencimientos? ¿Hay relación estructurada con financiadores? ¿Se anticipan necesidades de refinanciación? ¿Se controla documentación? | R11: Contratos de deuda; covenant tracker; calendario de vencimientos; reportes a bancos; actas; forecasts; documentación financiera. | S11: Implantar gestión integrada de deuda con seguimiento de covenants, alertas, previsión, repositorio documental y estrategia de relación bancaria.
A12: Mercados de deuda y capitales | B12: 3.3 Acceso a mercados, instrumentos y ejecución de operaciones | C12: Evaluar la capacidad para evaluar, seleccionar y ejecutar instrumentos de deuda/capital de acuerdo con necesidades financieras y condiciones de mercado. | D12: Selección de instrumentos financiera caso a caso, con análisis limitado de alternativas, costes, riesgos y ejecución. | E12: Comparativas básicas entre fuentes de financiación, aunque con criterios poco homogéneos y dependencia de asesores externos. | F12: Metodología de evaluación de instrumentos con coste, riesgo, vencimiento, flexibilidad, covenants, mercado y proceso de aprobación. | G12: Ejecución integrada con estrategia de financiación, ventanas de mercado, rating, inversores, bancos, riesgos y reporting de operación. | H12: IA analiza condiciones de mercado, simula alternativas de instrumentos y recomienda momento, estructura y fuentes óptimas de financiación. | I12: Agentes de IA para trading y simulación de mercado; Generación de estrategias de inversión; Valoración predictiva de la compañía | M12: =IF(COUNT(J12:L12)=0,"",ROUND(AVERAGE(J12:L12),0)) | N12: =IF(M12="","",CHOOSE(M12,"1 - Inicial","2 - Estructurado","3 - Estandarizado","4 - Optimizado","5 - Avanzado/Referente")) | O12: =IF(M12="","",MAX(0,4-M12)) | P12: =IF(O12="","",IF(O12>=3,"Alta",IF(O12=2,"Media",IF(O12=1,"Media","Baja")))) | Q12: ¿Se comparan fuentes e instrumentos? ¿Se analizan coste, riesgo y flexibilidad? ¿Se evalúan ventanas de mercado? ¿Existe proceso de aprobación? | R12: Análisis de alternativas; term sheets; comparativas de coste; aprobaciones; rating; investor/bank materials; documentación de operación. | S12: Crear metodología de evaluación y ejecución de instrumentos financieros con escenarios de mercado, coste y riesgo, aprobaciones y lecciones aprendidas.
A13: Mercados de deuda y capitales | B13: 3.4 Reporting de capital markets e inteligencia de financiación | C13: Evaluar si Tesorería monitoriza mercados, condiciones financieras, apetito inversor/bancario y oportunidades de financiación. | D13: Monitorización de mercados puntual y manual, con baja sistematización de señales y oportunidades. | E13: Seguimiento básico de tipos, spreads y noticias de mercado, aunque con análisis irregular y baja conexión con decisiones. | F13: Market intelligence financiero con fuentes, indicadores, benchmarks, reporting periódico y responsables. | G13: Inteligencia integrada con estrategia de financiación, deuda, inversión, riesgos, escenarios y decisiones de timing. | H13: IA sintetiza señales de mercado, detecta oportunidades de financiación, genera alertas y recomienda acciones de mercados de capitales. | I13: Inteligencia de mercado; Generación de estrategias de inversión; Agentes de IA para trading y simulación de mercado | M13: =IF(COUNT(J13:L13)=0,"",ROUND(AVERAGE(J13:L13),0)) | N13: =IF(M13="","",CHOOSE(M13,"1 - Inicial","2 - Estructurado","3 - Estandarizado","4 - Optimizado","5 - Avanzado/Referente")) | O13: =IF(M13="","",MAX(0,4-M13)) | P13: =IF(O13="","",IF(O13>=3,"Alta",IF(O13=2,"Media",IF(O13=1,"Media","Baja")))) | Q13: ¿Se monitorizan mercados de deuda/capitales? ¿Existen benchmarks y señales clave? ¿Se conecta con decisiones de financiación? ¿Se generan alertas? | R13: Reportes de mercado; benchmarks; curvas de tipos; spreads; actas de comité; recomendaciones de financiación; alertas. | S13: Implantar inteligencia de mercados de capitales con fuentes, indicadores, alertas, referencias de mercado y conexión con la estrategia de financiación.
... A21: Inversiones | B21: 5.4 Reporting, cumplimiento y control de inversiones | C21: Evaluar si las inversiones se reportan y controlan con criterios de cumplimiento, límites, performance, riesgos y evidencias de decisión. | D21: Reporting de inversiones manual y disperso, con baja trazabilidad de decisiones, límites y cumplimiento de política. | E21: Reportes periódicos básicos, aunque con controles manuales de límites y documentación parcial. | F21: Reporting estándar de inversiones con rentabilidad, riesgo, límites, cumplimiento, vencimientos, contrapartes y aprobaciones. | G21: Control integrado con workflows, alertas de límites, evidencias, accounting, compliance y revisión de performance. | H21: IA genera los informes ejecutivos, detecta incumplimientos potenciales, explica las variaciones y recomienda acciones correctivas. | I21: Visión ejecutiva de la salud financiera; Analista digital de Finanzas bajo demanda; Monitorización predictiva del cumplimiento | M21: =IF(COUNT(J21:L21)=0,"",ROUND(AVERAGE(J21:L21),0)) | N21: =IF(M21="","",CHOOSE(M21,"1 - Inicial","2 - Estructurado","3 - Estandarizado","4 - Optimizado","5 - Avanzado/Referente")) | O21: =IF(M21="","",MAX(0,4-M21)) | P21: =IF(O21="","",IF(O21>=3,"Alta",IF(O21=2,"Media",IF(O21=1,"Media","Baja")))) | Q21: ¿Se reporta cumplimiento de política? ¿Se controlan límites y excepciones? ¿Se documentan decisiones? ¿Se explica performance? | R21: Reporting de inversiones; policy compliance; excepciones; aprobaciones; logs; actas de comité; análisis de rendimiento/riesgo. | S21: Crear informes y control de inversiones con límites, evidencias, alertas, rentabilidad, cumplimiento y decisiones trazables.

Sheet Resumen
A1: Capacidad | B1: Score Procesos | C1: Score Tecnología | D1: Score Organización | E1: Score Medio | F1: Gap vs objetivo | G1: Prioridad
A2: Control y tratamiento contable | B2: =IFERROR(ROUND(AVERAGEIF(Assessment!$A:$A,A2,Assessment!$J:$J),0),"") | C2: =IFERROR(ROUND(AVERAGEIF(Assessment!$A:$A,A2,Assessment!$K:$K),0),"") | D2: =IFERROR(ROUND(AVERAGEIF(Assessment!$A:$A,A2,Assessment!$L:$L),0),"") | E2: =IFERROR(ROUND(AVERAGE(B2:D2),0),"") | F2: =IF(E2="","",MAX(0,4-E2)) | G2: =IF(F2="","",IF(F2>=3,"Alta",IF(F2=2,"Media",IF(F2=1,"Media","Baja"))))
A3: Gestión de riesgos financieros | B3: =IFERROR(ROUND(AVERAGEIF(Assessment!$A:$A,A3,Assessment!$J:$J),0),"") | C3: =IFERROR(ROUND(AVERAGEIF(Assessment!$A:$A,A3,Assessment!$K:$K),0),"") | D3: =IFERROR(ROUND(AVERAGEIF(Assessment!$A:$A,A3,Assessment!$L:$L),0),"") | E3: =IFERROR(ROUND(AVERAGE(B3:D3),0),"") | F3: =IF(E3="","",MAX(0,4-E3)) | G3: =IF(F3="","",IF(F3>=3,"Alta",IF(F3=2,"Media",IF(F3=1,"Media","Baja"))))
A4: Mercados de deuda y capitales | B4: =IFERROR(ROUND(AVERAGEIF(Assessment!$A:$A,A4,Assessment!$J:$J),0),"") | C4: =IFERROR(ROUND(AVERAGEIF(Assessment!$A:$A,A4,Assessment!$K:$K),0),"") | D4: =IFERROR(ROUND(AVERAGEIF(Assessment!$A:$A,A4,Assessment!$L:$L),0),"") | E4: =IFERROR(ROUND(AVERAGE(B4:D4),0),"") | F4: =IF(E4="","",MAX(0,4-E4)) | G4: =IF(F4="","",IF(F4>=3,"Alta",IF(F4=2,"Media",IF(F4=1,"Media","Baja"))))
A5: Gestión de cash flow y reporte | B5: =IFERROR(ROUND(AVERAGEIF(Assessment!$A:$A,A5,Assessment!$J:$J),0),"") | C5: =IFERROR(ROUND(AVERAGEIF(Assessment!$A:$A,A5,Assessment!$K:$K),0),"") | D5: =IFERROR(ROUND(AVERAGEIF(Assessment!$A:$A,A5,Assessment!$L:$L),0),"") | E5: =IFERROR(ROUND(AVERAGE(B5:D5),0),"") | F5: =IF(E5="","",MAX(0,4-E5)) | G5: =IF(F5="","",IF(F5>=3,"Alta",IF(F5=2,"Media",IF(F5=1,"Media","Baja"))))
A6: Inversiones | B6: =IFERROR(ROUND(AVERAGEIF(Assessment!$A:$A,A6,Assessment!$J:$J),0),"") | C6: =IFERROR(ROUND(AVERAGEIF(Assessment!$A:$A,A6,Assessment!$K:$K),0),"") | D6: =IFERROR(ROUND(AVERAGEIF(Assessment!$A:$A,A6,Assessment!$L:$L),0),"") | E6: =IFERROR(ROUND(AVERAGE(B6:D6),0),"") | F6: =IF(E6="","",MAX(0,4-E6)) | G6: =IF(F6="","",IF(F6>=3,"Alta",IF(F6=2,"Media",IF(F6=1,"Media","Baja"))))
A7: Score global dominio | B7: =IFERROR(ROUND(AVERAGE(B2:B6),0),"") | C7: =IFERROR(ROUND(AVERAGE(C2:C6),0),"") | D7: =IFERROR(ROUND(AVERAGE(D2:D6),0),"") | E7: =IFERROR(ROUND(AVERAGE(E2:E6),0),"") | F7: =IF(E7="","",MAX(0,4-E7)) | G7: =IF(F7="","",IF(F7>=3,"Alta",IF(F7=2,"Media",IF(F7=1,"Media","Baja"))))

Sheet Heatmap
A1: Capacidad | B1: Subcapacidad | C1: Procesos | D1: Tecnología | E1: Organización | F1: Score medio | G1: Gap | H1: Prioridad
A2: Control y tratamiento contable | B2: 1.1 Gobierno del tratamiento contable de operaciones de tesorería | C2: =Assessment!J2 -> 0 | D2: =Assessment!K2 -> 0 | E2: =Assessment!L2 -> 0 | F2: =Assessment!M2 | G2: =Assessment!O2 | H2: =Assessment!P2
A3: Control y tratamiento contable | B3: 1.2 Registro, conciliación y devengo de intereses y comisiones | C3: =Assessment!J3 -> 0 | D3: =Assessment!K3 -> 0 | E3: =Assessment!L3 -> 0 | F3: =Assessment!M3 | G3: =Assessment!O3 | H3: =Assessment!P3
A4: Control y tratamiento contable | B4: 1.3 Calidad del dato maestro financiero y bancario | C4: =Assessment!J4 -> 0 | D4: =Assessment!K4 -> 0 | E4: =Assessment!L4 -> 0 | F4: =Assessment!M4 | G4: =Assessment!O4 | H4: =Assessment!P4
A5: Control y tratamiento contable | B5: 1.4 Reporting financiero de resultados de tesorería | C5: =Assessment!J5 -> 0 | D5: =Assessment!K5 -> 0 | E5: =Assessment!L5 -> 0 | F5: =Assessment!M5 | G5: =Assessment!O5 | H5: =Assessment!P5
A6: Gestión de riesgos financieros | B6: 2.1 Marco de gestión de riesgos financieros y políticas | C6: =Assessment!J6 -> 0 | D6: =Assessment!K6 -> 0 | E6: =Assessment!L6 -> 0 | F6: =Assessment!M6 | G6: =Assessment!O6 | H6: =Assessment!P6
A7: Gestión de riesgos financieros | B7: 2.2 Medición y cobertura de riesgo de divisa | C7: =Assessment!J7 -> 0 | D7: =Assessment!K7 -> 0 | E7: =Assessment!L7 -> 0 | F7: =Assessment!M7 | G7: =Assessment!O7 | H7: =Assessment!P7
A8: Gestión de riesgos financieros | B8: 2.3 Gestión de riesgo de tipos, contraparte y crédito financiero | C8: =Assessment!J8 -> 0 | D8: =Assessment!K8 -> 0 | E8: =Assessment!L8 -> 0 | F8: =Assessment!M8 | G8: =Assessment!O8 | H8: =Assessment!P8
A9: Gestión de riesgos financieros | B9: 2.4 Escenarios, stress testing y reporting de riesgos financieros | C9: =Assessment!J9 -> 0 | D9: =Assessment!K9 -> 0 | E9: =Assessment!L9 -> 0 | F9: =Assessment!M9 | G9: =Assessment!O9 | H9: =Assessment!P9
A10: Mercados de deuda y capitales | B10: 3.1 Estrategia de financiación y estructura de capital | C10: =Assessment!J10 -> 0 | D10: =Assessment!K10 -> 0 | E10: =Assessment!L10 -> 0 | F10: =Assessment!M10 | G10: =Assessment!O10 | H10: =Assessment!P10
A11: Mercados de deuda y capitales | B11: 3.2 Gestión de deuda, covenants y relación con financiadores | C11: =Assessment!J11 -> 0 | D11: =Assessment!K11 -> 0 | E11: =Assessment!L11 -> 0 | F11: =Assessment!M11 | G11: =Assessment!O11 | H11: =Assessment!P11
A12: Mercados de deuda y capitales | B12: 3.3 Acceso a mercados, instrumentos y ejecución de operaciones | C12: =Assessment!J12 -> 0 | D12: =Assessment!K12 -> 0 | E12: =Assessment!L12 -> 0 | F12: =Assessment!M12 | G12: =Assessment!O12 | H12: =Assessment!P12
A13: Mercados de deuda y capitales | B13: 3.4 Reporting de capital markets e inteligencia de financiación | C13: =Assessment!J13 -> 0 | D13: =Assessment!K13 -> 0 | E13: =Assessment!L13 -> 0 | F13: =Assessment!M13 | G13: =Assessment!O13 | H13: =Assessment!P13
... A21: Inversiones | B21: 5.4 Reporting, cumplimiento y control de inversiones | C21: =Assessment!J21 -> 0 | D21: =Assessment!K21 -> 0 | E21: =Assessment!L21 -> 0 | F21: =Assessment!M21 | G21: =Assessment!O21 | H21: =Assessment!P21

Sheet Roadmap
A1: Capacidad | B1: Subcapacidad | C1: Gap | D1: Prioridad | E1: Iniciativa sugerida | F1: Casos AI asociados | G1: Oleada | H1: Owner | I1: Estado | J1: Comentarios
A2: Control y tratamiento contable | B2: 1.1 Gobierno del tratamiento contable de operaciones de tesorería | C2: =Assessment!O2 | D2: =Assessment!P2 | E2: Definir gobierno del tratamiento contable de tesorería con políticas, controles, trazabilidad, responsables y revisión recurrente de excepciones. | F2: Detección de asientos inusuales en el cierre; Detección de inconsistencias en datos maestros; Análisis de desviaciones con explicación automática | G2: =IF(C2="","",IF(C2>=3,"Oleada 1",IF(C2=2,"Oleada 2",IF(C2=1,"Oleada 3","")))) | I2: No iniciado
A3: Control y tratamiento contable | B3: 1.2 Registro, conciliación y devengo de intereses y comisiones | C3: =Assessment!O3 | D3: =Assessment!P3 | E3: Implantar modelo de devengo y conciliación de intereses/comisiones con reglas, fuentes oficiales, controles y alertas de omisiones. | F3: Detección de provisiones omitidas; Análisis de desviaciones con explicación automática; Conciliación a nivel de transacción | G3: =IF(C3="","",IF(C3>=3,"Oleada 1",IF(C3=2,"Oleada 2",IF(C3=1,"Oleada 3","")))) | I3: No iniciado
A4: Control y tratamiento contable | B4: 1.3 Calidad del dato maestro financiero y bancario | C4: =Assessment!O4 | D4: =Assessment!P4 | E4: Implantar gobierno de datos maestros financieros y bancarios con responsables, flujo de trabajo, controles automáticos, trazabilidad y gestión de incidencias. | F4: Detección de inconsistencias en datos maestros; Flujos guiados de cambio en datos maestros; Generación de documentación de metadatos | G4: =IF(C4="","",IF(C4>=3,"Oleada 1",IF(C4=2,"Oleada 2",IF(C4=1,"Oleada 3","")))) | I4: No iniciado
A5: Control y tratamiento contable | B5: 1.4 Reporting financiero de resultados de tesorería | C5: =Assessment!O5 | D5: =Assessment!P5 | E5: Crear informes financieros de tesorería con drivers, KPIs, narrativa ejecutiva, conexión con la previsión y recomendaciones de acción. | F5: Visión ejecutiva de la salud financiera; Análisis de desviaciones con explicación automática; Analista digital de Finanzas bajo demanda | G5: =IF(C5="","",IF(C5>=3,"Oleada 1",IF(C5=2,"Oleada 2",IF(C5=1,"Oleada 3","")))) | I5: No iniciado
A6: Gestión de riesgos financieros | B6: 2.1 Marco de gestión de riesgos financieros y políticas | C6: =Assessment!O6 | D6: =Assessment!P6 | E6: Definir marco integral de riesgos financieros con políticas, límites, métricas, informes, gobierno y flujo de excepciones. | F6: Optimización de operaciones de divisa; Agentes de IA para análisis de riesgo crediticio; Monitorización predictiva del cumplimiento | G6: =IF(C6="","",IF(C6>=3,"Oleada 1",IF(C6=2,"Oleada 2",IF(C6=1,"Oleada 3","")))) | I6: No iniciado
A7: Gestión de riesgos financieros | B7: 2.2 Medición y cobertura de riesgo de divisa | C7: =Assessment!O7 | D7: =Assessment!P7 | E7: Implantar modelo de gestión del riesgo de divisa con previsión de exposición, límites, escenarios, seguimiento de coberturas y recomendaciones de mitigación. | F7: Optimización de operaciones de divisa; Generación de estrategias de inversión | G7: =IF(C7="","",IF(C7>=3,"Oleada 1",IF(C7=2,"Oleada 2",IF(C7=1,"Oleada 3","")))) | I7: No iniciado
A8: Gestión de riesgos financieros | B8: 2.3 Gestión de riesgo de tipos, contraparte y crédito financiero | C8: =Assessment!O8 | D8: =Assessment!P8 | E8: Diseñar modelo de gestión de riesgo de tipos y contraparte con límites, sensibilidad, escenarios, alertas y decisiones de cobertura/diversificación. | F8: Agentes de IA para análisis de riesgo crediticio; Valoración predictiva de la compañía | G8: =IF(C8="","",IF(C8>=3,"Oleada 1",IF(C8=2,"Oleada 2",IF(C8=1,"Oleada 3","")))) | I8: No iniciado
A9: Gestión de riesgos financieros | B9: 2.4 Escenarios, stress testing y reporting de riesgos financieros | C9: =Assessment!O9 | D9: =Assessment!P9 | E9: Crear marco de pruebas de estrés financieras con variables clave, impactos, alertas y planes de respuesta. | F9: Previsión predictiva de flujo de caja; Optimización de operaciones de divisa; Patrones históricos para predecir el rendimiento | G9: =IF(C9="","",IF(C9>=3,"Oleada 1",IF(C9=2,"Oleada 2",IF(C9=1,"Oleada 3","")))) | I9: No iniciado
A10: Mercados de deuda y capitales | B10: 3.1 Estrategia de financiación y estructura de capital | C10: =Assessment!O10 | D10: =Assessment!P10 | E10: Definir estrategia de financiación y estructura de capital con escenarios, vencimientos, coste, covenants, rating y conexión con plan estratégico. | F10: Generación de estrategias de inversión; Valoración predictiva de la compañía; Visión ejecutiva de la salud financiera | G10: =IF(C10="","",IF(C10>=3,"Oleada 1",IF(C10=2,"Oleada 2",IF(C10=1,"Oleada 3","")))) | I10: No iniciado
A11: Mercados de deuda y capitales | B11: 3.2 Gestión de deuda, covenants y relación con financiadores | C11: =Assessment!O11 | D11: =Assessment!P11 | E11: Implantar gestión integrada de deuda con seguimiento de covenants, alertas, previsión, repositorio documental y estrategia de relación bancaria. | F11: Visión ejecutiva de la salud financiera; Previsión predictiva de flujo de caja; Informes de investigación y KYC | G11: =IF(C11="","",IF(C11>=3,"Oleada 1",IF(C11=2,"Oleada 2",IF(C11=1,"Oleada 3","")))) | I11: No iniciado
A12: Mercados de deuda y capitales | B12: 3.3 Acceso a mercados, instrumentos y ejecución de operaciones | C12: =Assessment!O12 | D12: =Assessment!P12 | E12: Crear metodología de evaluación y ejecución de instrumentos financieros con escenarios de mercado, coste y riesgo, aprobaciones y lecciones aprendidas. | F12: Agentes de IA para trading y simulación de mercado; Generación de estrategias de inversión; Valoración predictiva de la compañía | G12: =IF(C12="","",IF(C12>=3,"Oleada 1",IF(C12=2,"Oleada 2",IF(C12=1,"Oleada 3","")))) | I12: No iniciado
A13: Mercados de deuda y capitales | B13: 3.4 Reporting de capital markets e inteligencia de financiación | C13: =Assessment!O13 | D13: =Assessment!P13 | E13: Implantar inteligencia de mercados de capitales con fuentes, indicadores, alertas, referencias de mercado y conexión con la estrategia de financiación. | F13: Inteligencia de mercado; Generación de estrategias de inversión; Agentes de IA para trading y simulación de mercado | G13: =IF(C13="","",IF(C13>=3,"Oleada 1",IF(C13=2,"Oleada 2",IF(C13=1,"Oleada 3","")))) | I13: No iniciado
... A21: Inversiones | B21: 5.4 Reporting, cumplimiento y control de inversiones | C21: =Assessment!O21 | D21: =Assessment!P21 | E21: Crear informes y control de inversiones con límites, evidencias, alertas, rentabilidad, cumplimiento y decisiones trazables. | F21: Visión ejecutiva de la salud financiera; Analista digital de Finanzas bajo demanda; Monitorización predictiva del cumplimiento | G21: =IF(C21="","",IF(C21>=3,"Oleada 1",IF(C21=2,"Oleada 2",IF(C21=1,"Oleada 3","")))) | I21: No iniciado

Sheet AI Overlay
A1: Capacidad | B1: Subcapacidad | C1: Casos de uso AI asociados | D1: Aplicación en nivel avanzado | E1: Fuente
A2: Control y tratamiento contable | B2: 1.1 Gobierno del tratamiento contable de operaciones de tesorería | C2: Detección de asientos inusuales en el cierre; Detección de inconsistencias en datos maestros; Análisis de desviaciones con explicación automática | D2: Modelo basado en IA que detecta tratamientos anómalos, sugiere clasificaciones contables y explica variaciones de resultados financieros. | E2: F3M_AI_Mapping_Consolidado_v1.xlsx
A3: Control y tratamiento contable | B3: 1.2 Registro, conciliación y devengo de intereses y comisiones | C3: Detección de provisiones omitidas; Análisis de desviaciones con explicación automática; Conciliación a nivel de transacción | D3: IA identifica devengos esperados, detecta omisiones o anomalías y genera explicaciones inteligentes de variaciones financieras. | E3: F3M_AI_Mapping_Consolidado_v1.xlsx
A4: Control y tratamiento contable | B4: 1.3 Calidad del dato maestro financiero y bancario | C4: Detección de inconsistencias en datos maestros; Flujos guiados de cambio en datos maestros; Generación de documentación de metadatos | D4: IA detecta inconsistencias en datos maestros, propone remediación y guía flujos de trabajo adaptativos de cambios financieros/bancarios. | E4: F3M_AI_Mapping_Consolidado_v1.xlsx
A5: Control y tratamiento contable | B5: 1.4 Reporting financiero de resultados de tesorería | C5: Visión ejecutiva de la salud financiera; Análisis de desviaciones con explicación automática; Analista digital de Finanzas bajo demanda | D5: Informes basados en IA, con narrativa automática, explicación de los drivers, alertas tempranas y recomendaciones sobre coste financiero y liquidez. | E5: F3M_AI_Mapping_Consolidado_v1.xlsx
A6: Gestión de riesgos financieros | B6: 2.1 Marco de gestión de riesgos financieros y políticas | C6: Optimización de operaciones de divisa; Agentes de IA para análisis de riesgo crediticio; Monitorización predictiva del cumplimiento | D6: Modelo basado en IA que monitoriza exposiciones, detecta desviaciones frente a límites y recomienda acciones de cobertura o mitigación. | E6: F3M_AI_Mapping_Consolidado_v1.xlsx
A7: Gestión de riesgos financieros | B7: 2.2 Medición y cobertura de riesgo de divisa | C7: Optimización de operaciones de divisa; Generación de estrategias de inversión | D7: IA identifica patrones de tipo de cambio, anticipa exposición, simula escenarios y recomienda estrategias de cobertura según riesgo, coste y política. | E7: F3M_AI_Mapping_Consolidado_v1.xlsx
A8: Gestión de riesgos financieros | B8: 2.3 Gestión de riesgo de tipos, contraparte y crédito financiero | C8: Agentes de IA para análisis de riesgo crediticio; Valoración predictiva de la compañía | D8: IA calcula sensibilidades, anticipa cambios de riesgo, alerta sobre límites y recomienda acciones de refinanciación, cobertura o diversificación. | E8: F3M_AI_Mapping_Consolidado_v1.xlsx
A9: Gestión de riesgos financieros | B9: 2.4 Escenarios, stress testing y reporting de riesgos financieros | C9: Previsión predictiva de flujo de caja; Optimización de operaciones de divisa; Patrones históricos para predecir el rendimiento | D9: IA simula escenarios dinámicos, identifica alertas tempranas, estima impactos y recomienda respuestas financieras preventivas. | E9: F3M_AI_Mapping_Consolidado_v1.xlsx
A10: Mercados de deuda y capitales | B10: 3.1 Estrategia de financiación y estructura de capital | C10: Generación de estrategias de inversión; Valoración predictiva de la compañía; Visión ejecutiva de la salud financiera | D10: IA recomienda estrategias de financiación considerando mercado, coste de capital, rating, liquidez, escenarios y objetivos corporativos. | E10: F3M_AI_Mapping_Consolidado_v1.xlsx
A11: Mercados de deuda y capitales | B11: 3.2 Gestión de deuda, covenants y relación con financiadores | C11: Visión ejecutiva de la salud financiera; Previsión predictiva de flujo de caja; Informes de investigación y KYC | D11: IA anticipa riesgos de covenant, recomienda acciones de refinanciación y sintetiza documentación financiera para financiadores. | E11: F3M_AI_Mapping_Consolidado_v1.xlsx
A12: Mercados de deuda y capitales | B12: 3.3 Acceso a mercados, instrumentos y ejecución de operaciones | C12: Agentes de IA para trading y simulación de mercado; Generación de estrategias de inversión; Valoración predictiva de la compañía | D12: IA analiza condiciones de mercado, simula alternativas de instrumentos y recomienda momento, estructura y fuentes óptimas de financiación. | E12: F3M_AI_Mapping_Consolidado_v1.xlsx
... A21: Inversiones | B21: 5.4 Reporting, cumplimiento y control de inversiones | C21: Visión ejecutiva de la salud financiera; Analista digital de Finanzas bajo demanda; Monitorización predictiva del cumplimiento | D21: IA genera los informes ejecutivos, detecta incumplimientos potenciales, explica las variaciones y recomienda acciones correctivas. | E21: F3M_AI_Mapping_Consolidado_v1.xlsx

Sheet Guias scoring
A1: GUÍAS DE SCORING F3M
A2: PROCESOS
A3: Nivel 1 - Inicial | B3: Proceso inexistente, manual o ad hoc.
A4: Nivel 2 - Estructurado | B4: Proceso parcial, definido con variabilidad y dependencias manuales.
A5: Nivel 3 - Estandarizado | B5: Proceso documentado, homogéneo y repetible.
A6: Nivel 4 - Optimizado | B6: Proceso medido, eficiente, con controles y mejora continua.
A7: Nivel 5 - Avanzado | B7: Proceso integrado end-to-end, orientado a decisión y habilitado por automatización/AI cuando aplique.
A9: TECNOLOGÍA
A10: Nivel 1 - Inicial | B10: Excel/manual, sin integración.
A11: Nivel 2 - Estructurado | B11: Herramientas parciales o locales, con baja integración.
A12: Nivel 3 - Estandarizado | B12: Herramienta corporativa y reglas definidas.
A13: Nivel 4 - Optimizado | B13: Integración end-to-end, automatización y controles tecnológicos.
A14: Nivel 5 - Avanzado | B14: Analítica avanzada, AI/GenAI, detección predictiva, autoservicio o workflow inteligente.
A16: ORGANIZACIÓN
A17: Nivel 1 - Inicial | B17: Roles poco claros y alta dependencia de personas.
A18: Nivel 2 - Estructurado | B18: Roles parcialmente definidos y coordinación manual.
A19: Nivel 3 - Estandarizado | B19: Roles, ownership y accountability claros.
A20: Nivel 4 - Optimizado | B20: Organización alineada con procesos, KPIs y mejora continua.
A21: Nivel 5 - Avanzado | B21: Equipos orientados a gestión de liquidez, riesgos financieros, mercados y generación de valor.
A23: REGLAS DE ORO
A24: 1 | B24: Puntuar el estado actual, no el objetivo.
A25: 2 | B25: No mezclar palancas: procesos, tecnología y organización se puntúan por separado.
A26: 3 | B26: Sustentar cada score con evidencias.
A27: 4 | B27: No sobrevalorar la tecnología si el proceso o la adopción no están maduros.

Sheet Instrucciones
A1: F3M - Tesorería | Assessment-ready con AI
A2: Uso del fichero | B2: 1. En Assessment, puntuar cada subcapacidad en las tres palancas: Procesos, Tecnología y Organización. 2. Utilizar valores enteros de 1 a 5, donde 1 = Inicial y 5 = Avanzado/Referente. 3. El Score Medio, Nivel resultante, Gap y Prioridad se calculan automáticamente. 4. Objetivo de madurez utilizado para el gap: Nivel 4 - Optimizado. 5. Resumen consolida resultados por capacidad y gráfico ejecutivo. 6. Heatmap facilita la lectura visual por subcapacidad y palanca. 7. Roadmap convierte gaps en iniciativas sugeridas y oleadas.
A3: Dominio | B3: Tesorería: Control y tratamiento contable, Gestión de riesgos financieros, Mercados de deuda y capitales, Gestión de cash flow y reporte e Inversiones.
A4: Escala F3M | B4: 1 - Inicial: modelo básico, reactivo, heterogéneo y poco formalizado. 2 - Estructurado: prácticas definidas, con consistencia parcial y dependencias manuales. 3 - Estandarizado: modelo homogéneo, documentado, consistente y controlado. 4 - Optimizado: modelo integrado, medido, con mejora continua y foco en eficiencia/control. 5 - Avanzado/Referente: modelo maduro, predictivo, AI-enabled y orientado a liquidez, riesgo y valor.
A5: AI Overlay | B5: Los casos de uso AI se han mapeado desde F3M_AI_Mapping_Consolidado_v1.xlsx. En capacidades con cobertura limitada se han usado casos por analogía funcional, especialmente para reporting financiero y datos maestros de tesorería.
A6: Buenas prácticas | B6: Evaluar situación actual, sustentar el score con evidencias, separar las tres palancas, validar resultados con responsables de Tesorería y preservar la conexión entre liquidez, riesgos, financiación e inversiones.
