Workbook

Sheet Assessment
A1: Capacidad | B1: Subcapacidad | C1: Objetivo de evaluación | D1: Nivel 1 - Inicial | E1: Nivel 2 - Estructurado | F1: Nivel 3 - Estandarizado | G1: Nivel 4 - Optimizado | H1: Nivel 5 - Avanzado/Referente | I1: Casos de uso AI asociados | J1: Score Procesos | K1: Score Tecnología | L1: Score Organización | M1: Score Medio | N1: Nivel resultante | O1: Gap vs objetivo | P1: Prioridad | Q1: Preguntas clave | R1: Evidencias | S1: Iniciativa sugerida | T1: Comentarios / hallazgos
A2: Source-to-Pay | B2: 1.1 Estrategia de compras, categorías y demanda | C2: Evaluar si la organización planifica la demanda de compras, gestiona categorías y conecta sourcing con necesidades del negocio. | D2: Compras reactivas, sin visión de demanda ni planificación por categoría. | E2: Categorías básicas y demanda estimada de forma parcial, con alta dependencia de peticiones ad hoc. | F2: Modelo de categorías y planificación de demanda definido, con criterios de priorización y responsables. | G2: Planificación integrada con negocio, contratos y presupuestos, con análisis de gasto y demanda recurrente. | H2: Planificación predictiva del gasto y la demanda de terceros a partir de contratos, histórico y señales externas, con recomendación de aprovisionamiento y de calendario. | I2: Previsión del gasto contratado con terceros; Planificación logística resiliente | M2: =IF(COUNTA(J2:L2)=0,"",ROUND(AVERAGE(J2:L2),2)) | N2: =IF(M2="","",IF(M2<1.5,"1 - Inicial",IF(M2<2.5,"2 - Estructurado",IF(M2<3.5,"3 - Estandarizado",IF(M2<4.5,"4 - Optimizado","5 - Avanzado/Referente"))))) | O2: =IF(M2="","",MAX(0,4-M2)) | P2: =IF(M2="","",IF(O2>=2,"Alta",IF(O2>=1,"Media","Baja"))) | Q2: ¿Existe planificación de demanda de compras? ¿Se trabaja por categorías? ¿Se conecta con presupuesto/forecast? ¿Se anticipan necesidades recurrentes? | R2: Plan de compras; category plans; forecast de gasto; contratos; presupuestos; análisis spend. | S2: Implantar planificación de demanda de compras por categoría con previsión de gasto contractual y conexión con presupuesto.
A3: Source-to-Pay | B3: 1.2 Selección, evaluación y gestión de proveedores | C3: Evaluar madurez del ciclo de evaluación, homologación, performance y riesgo de proveedores. | D3: Selección manual y reactiva de proveedores, sin criterios homogéneos ni evaluación recurrente. | E3: Homologación básica, con criterios documentados parcialmente y seguimiento limitado. | F3: Proceso estándar de evaluación, homologación y seguimiento de performance/proveedor. | G3: Gestión integrada de desempeño, riesgos, cumplimiento y oportunidades de mejora por proveedor. | H3: Motor de IA para evaluar proveedores y el riesgo de la cadena de suministro, con recomendación de selección y de negociación según desempeño, riesgo y contexto externo. | I3: Planificación logística resiliente; Evaluación de proveedores con IA; Redacción de contratos y pliegos; Insights sobre el dato de proveedor | M3: =IF(COUNTA(J3:L3)=0,"",ROUND(AVERAGE(J3:L3),2)) | N3: =IF(M3="","",IF(M3<1.5,"1 - Inicial",IF(M3<2.5,"2 - Estructurado",IF(M3<3.5,"3 - Estandarizado",IF(M3<4.5,"4 - Optimizado","5 - Avanzado/Referente"))))) | O3: =IF(M3="","",MAX(0,4-M3)) | P3: =IF(M3="","",IF(O3>=2,"Alta",IF(O3>=1,"Media","Baja"))) | Q3: ¿Hay criterios de homologación? ¿Se mide performance? ¿Se evalúa riesgo proveedor? ¿Se usan datos externos? | R3: Scorecards proveedor; homologaciones; SLAs; incidencias; evaluación de riesgo; contratos. | S3: Crear modelo de inteligencia de proveedores con indicadores de desempeño, riesgo, cumplimiento y recomendaciones de aprovisionamiento.
A4: Source-to-Pay | B4: 1.3 Gestión contractual, RFPs y SoWs | C4: Evaluar si la función gestiona contratos, RFPs y SoWs de forma estructurada, trazable y eficiente. | D4: Contratos y RFPs manuales, dispersos y poco trazables. | E4: Plantillas básicas y repositorio parcial, con revisión manual intensiva. | F4: Proceso estándar para RFPs, contratos y SoWs, con plantillas, aprobaciones y repositorio central. | G4: Gestión contractual integrada con compras, legal, presupuesto y proveedores, con alertas y trazabilidad de cambios. | H4: Asistente IA para generar RFP, contratos y SoW, extraer cláusulas, analizar riesgos y recomendar condiciones financieras/comerciales. | I4: Redacción de contratos y pliegos; Asistente de RFP y de conocimiento comercial; Previsión del gasto contratado con terceros | M4: =IF(COUNTA(J4:L4)=0,"",ROUND(AVERAGE(J4:L4),2)) | N4: =IF(M4="","",IF(M4<1.5,"1 - Inicial",IF(M4<2.5,"2 - Estructurado",IF(M4<3.5,"3 - Estandarizado",IF(M4<4.5,"4 - Optimizado","5 - Avanzado/Referente"))))) | O4: =IF(M4="","",MAX(0,4-M4)) | P4: =IF(M4="","",IF(O4>=2,"Alta",IF(O4>=1,"Media","Baja"))) | Q4: ¿Existe repositorio contractual? ¿Hay plantillas estándar? ¿Se analizan cláusulas financieras? ¿Se monitorizan vencimientos y obligaciones? | R4: Contratos; RFPs; SoWs; repositorio; workflow de aprobación; matriz de cláusulas; contratos vencidos. | S4: Implantar asistente contractual IA para generación, revisión y explotación financiera de contratos y SoWs.
A5: Source-to-Pay | B5: 1.4 Orden de compra, recepción y aprobación | C5: Evaluar el grado de control, automatización y cumplimiento del proceso desde solicitud hasta recepción/aprobación. | D5: Solicitudes, órdenes y aprobaciones manuales, con baja trazabilidad y controles débiles. | E5: Workflow parcial, autorizaciones básicas y controles manuales de recepción/factura. | F5: Proceso estándar de PR/PO, recepción y aprobaciones, con reglas y responsabilidades claras. | G5: Workflow integrado con catálogo, recepción, presupuesto, contrato y controles automáticos. | H5: IA recomienda momento óptimo de pagos/compras, detecta excepciones operativas y prioriza aprobaciones según impacto en caja, contrato y riesgo. | I5: Momento óptimo de pago a proveedores; Recomendaciones de resolución de incidencias; Flujos guiados de cambio en datos maestros; Detección de facturas duplicadas | M5: =IF(COUNTA(J5:L5)=0,"",ROUND(AVERAGE(J5:L5),2)) | N5: =IF(M5="","",IF(M5<1.5,"1 - Inicial",IF(M5<2.5,"2 - Estructurado",IF(M5<3.5,"3 - Estandarizado",IF(M5<4.5,"4 - Optimizado","5 - Avanzado/Referente"))))) | O5: =IF(M5="","",MAX(0,4-M5)) | P5: =IF(M5="","",IF(O5>=2,"Alta",IF(O5>=1,"Media","Baja"))) | Q5: ¿Qué % de compras tiene PO? ¿Se controlan recepciones? ¿Hay aprobaciones por umbrales? ¿Se detectan excepciones? | R5: PR/PO; workflow; recepción; aprobaciones; excepciones; controles presupuestarios. | S5: Digitalizar el flujo de solicitud, pedido y recepción con controles automáticos, excepciones y recomendaciones de aprobación y pago.
A6: Order-to-Cash | B6: 2.1 Gestión de pedidos, contratos y condiciones comerciales | C6: Evaluar si pedidos y condiciones comerciales se gestionan con control, trazabilidad y consistencia. | D6: Pedidos y condiciones gestionados manualmente, con dispersión de criterios y errores frecuentes. | E6: Proceso básico definido, aunque con validaciones manuales y excepciones recurrentes. | F6: Modelo estándar de entrada de pedidos, validación comercial y control de condiciones. | G6: Pedidos integrados con contratos, pricing, crédito, facturación y controles automáticos. | H6: Asistente IA analiza contratos/pedidos, valida obligaciones y condiciones comerciales, y recomienda acciones para evitar errores, fuga de ingresos o disputas. | I6: Lectura de contratos y obligaciones de desempeño; Detección de fugas de ingresos | M6: =IF(COUNTA(J6:L6)=0,"",ROUND(AVERAGE(J6:L6),2)) | N6: =IF(M6="","",IF(M6<1.5,"1 - Inicial",IF(M6<2.5,"2 - Estructurado",IF(M6<3.5,"3 - Estandarizado",IF(M6<4.5,"4 - Optimizado","5 - Avanzado/Referente"))))) | O6: =IF(M6="","",MAX(0,4-M6)) | P6: =IF(M6="","",IF(O6>=2,"Alta",IF(O6>=1,"Media","Baja"))) | Q6: ¿Qué validaciones existen sobre pedidos? ¿Se conectan contratos y pricing? ¿Se detectan condiciones atípicas? ¿Se controla leakage? | R6: Pedidos; contratos; pricing; aprobaciones; incidencias; ajustes comerciales; revenue leakage. | S6: Crear controles automáticos de pedido/contrato/precio con detección de condiciones atípicas y fugas de ingresos.
A7: Order-to-Cash | B7: 2.2 Facturación y emisión de documentos | C7: Evaluar automatización, exactitud, trazabilidad y control del proceso de facturación. | D7: Facturación manual, con errores frecuentes y correcciones reactivas. | E7: Plantillas y controles básicos, con validación manual relevante. | F7: Proceso de facturación estándar, con reglas documentadas y controles recurrentes. | G7: Facturación integrada con pedidos, contratos, impuestos, entregas y controles automáticos de error. | H7: Detección/corrección IA de errores de factura y generación de facturas personalizadas para pedidos no estándar, con validación fiscal/contable. | I7: Detección y corrección de errores en facturas; Facturación de pedidos no estándar | M7: =IF(COUNTA(J7:L7)=0,"",ROUND(AVERAGE(J7:L7),2)) | N7: =IF(M7="","",IF(M7<1.5,"1 - Inicial",IF(M7<2.5,"2 - Estructurado",IF(M7<3.5,"3 - Estandarizado",IF(M7<4.5,"4 - Optimizado","5 - Avanzado/Referente"))))) | O7: =IF(M7="","",MAX(0,4-M7)) | P7: =IF(M7="","",IF(O7>=2,"Alta",IF(O7>=1,"Media","Baja"))) | Q7: ¿Qué errores de factura son recurrentes? ¿La factura sale del pedido/contrato? ¿Hay validación fiscal? ¿Se mide first-time-right? | R7: Facturas; notas de crédito; errores; controles; logs de emisión; KPI first-time-right. | S7: Implantar motor IA de validación y corrección preventiva de facturas antes de emisión.
A8: Order-to-Cash | B8: 2.3 Cobros, aplicación de pagos y gestión de disputas | C8: Evaluar si los cobros, cash application y disputas se gestionan de forma eficiente y orientada a caja. | D8: Conciliación de cobros manual, disputas reactivas y baja visibilidad de aging. | E8: Proceso básico de cobros con seguimientos manuales y criterios variables. | F8: Modelo estándar de cash application, aging, dunning y gestión de disputas. | G8: Cash application automatizada, segmentación de cartera, workflow de disputas y control de aging/DSO. | H8: Un asistente de IA identifica las brechas de cobro, automatiza el contacto con el cliente, recomienda las condiciones de pago que mejoran el DSO y apoya la recuperación de ingresos y la gestión de disputas. | I8: Gestión asistida del recobro; Condiciones de pago óptimas para el DSO; Redacción de recursos ante denegaciones; Asistente financiero para el cliente | M8: =IF(COUNTA(J8:L8)=0,"",ROUND(AVERAGE(J8:L8),2)) | N8: =IF(M8="","",IF(M8<1.5,"1 - Inicial",IF(M8<2.5,"2 - Estructurado",IF(M8<3.5,"3 - Estandarizado",IF(M8<4.5,"4 - Optimizado","5 - Avanzado/Referente"))))) | O8: =IF(M8="","",MAX(0,4-M8)) | P8: =IF(M8="","",IF(O8>=2,"Alta",IF(O8>=1,"Media","Baja"))) | Q8: ¿Cómo se aplican cobros? ¿Se monitoriza DSO? ¿Hay workflow de disputas? ¿Se segmenta la cartera? | R8: Aging; DSO; cash application; disputas; recordatorios; comunicaciones; write-offs. | S8: Desplegar asistente inteligente de gestión de cobros con priorización, contacto automatizado con clientes y recomendaciones de condiciones.
A9: Order-to-Cash | B9: 2.4 Crédito, riesgo cliente y control de exposición | C9: Evaluar el control de crédito, límites, exposición y riesgo asociado a clientes. | D9: Límites de crédito informales o manuales, con revisiones esporádicas. | E9: Políticas básicas de crédito y revisión manual de excepciones. | F9: Modelo de crédito definido, con límites, aprobaciones y seguimiento periódico. | G9: Riesgo cliente integrado con pedidos, cobros, aging, límites y alertas de exposición. | H9: Puntuación dinámica con IA del cliente y del riesgo de cobro, con alertas tempranas y recomendación de bloqueo o liberación y de condiciones comerciales. | I9: Agentes de IA para análisis de riesgo crediticio; Predicción de retraso e impago; Condiciones de pago óptimas para el DSO | M9: =IF(COUNTA(J9:L9)=0,"",ROUND(AVERAGE(J9:L9),2)) | N9: =IF(M9="","",IF(M9<1.5,"1 - Inicial",IF(M9<2.5,"2 - Estructurado",IF(M9<3.5,"3 - Estandarizado",IF(M9<4.5,"4 - Optimizado","5 - Avanzado/Referente"))))) | O9: =IF(M9="","",MAX(0,4-M9)) | P9: =IF(M9="","",IF(O9>=2,"Alta",IF(O9>=1,"Media","Baja"))) | Q9: ¿Existen límites de crédito? ¿Se actualizan dinámicamente? ¿Se controla exposición? ¿Se anticipan impagos? | R9: Política de crédito; límites; aging; históricos de impago; aprobaciones; alertas de riesgo. | S9: Construir modelo predictivo de riesgo cliente con recomendaciones de límite, términos y acciones preventivas.
A10: Activos fijos / Gestión de activos | B10: 3.1 Alta, capitalización y clasificación de activos | C10: Evaluar el gobierno del alta, clasificación, capitalización y registro de activos fijos. | D10: Altas manuales, criterios variables y documentación incompleta. | E10: Proceso básico de alta y capitalización, con revisiones manuales puntuales. | F10: Políticas de capitalización y clasificación documentadas y aplicadas de forma consistente. | G10: Proceso integrado con compras, proyectos, contabilidad y control presupuestario. | H10: IA ayuda a clasificar gastos vs activos, detectar errores de codificación y generar metadatos/documentación de activos. | I10: Detección de errores de clasificación de gasto; Generación de documentación de metadatos; Flujos guiados de cambio en datos maestros | M10: =IF(COUNTA(J10:L10)=0,"",ROUND(AVERAGE(J10:L10),2)) | N10: =IF(M10="","",IF(M10<1.5,"1 - Inicial",IF(M10<2.5,"2 - Estructurado",IF(M10<3.5,"3 - Estandarizado",IF(M10<4.5,"4 - Optimizado","5 - Avanzado/Referente"))))) | O10: =IF(M10="","",MAX(0,4-M10)) | P10: =IF(M10="","",IF(O10>=2,"Alta",IF(O10>=1,"Media","Baja"))) | Q10: ¿Están claras las políticas CAPEX/OPEX? ¿Se registran altas con soporte completo? ¿Hay errores de clasificación? | R10: Política CAPEX; altas de activos; facturas; órdenes de compra; controles; maestro de activos. | S10: Implantar clasificación asistida CAPEX/OPEX y flujo de alta de activos con controles de soporte documental.
A11: Activos fijos / Gestión de activos | B11: 3.2 Inventario, localización y trazabilidad de activos | C11: Evaluar la exactitud del inventario físico/contable, localización y trazabilidad del ciclo de vida de activos. | D11: Inventario no actualizado, conciliaciones manuales y baja trazabilidad física/contable. | E11: Inventarios periódicos y conciliaciones básicas, con incidencias recurrentes. | F11: Inventario contable y físico conciliado de forma recurrente, con owners y evidencias. | G11: Trazabilidad integrada de altas, bajas, traslados, mantenimiento, ubicación y estado de activos. | H11: La IA, apoyada en sensorización digital, detecta inconsistencias y anomalías de activos y genera alertas sobre los activos críticos o no conciliados. | I11: Detección de inconsistencias en datos maestros; Acceso y extracción documental | M11: =IF(COUNTA(J11:L11)=0,"",ROUND(AVERAGE(J11:L11),2)) | N11: =IF(M11="","",IF(M11<1.5,"1 - Inicial",IF(M11<2.5,"2 - Estructurado",IF(M11<3.5,"3 - Estandarizado",IF(M11<4.5,"4 - Optimizado","5 - Avanzado/Referente"))))) | O11: =IF(M11="","",MAX(0,4-M11)) | P11: =IF(M11="","",IF(O11>=2,"Alta",IF(O11>=1,"Media","Baja"))) | Q11: ¿Existe inventario actualizado? ¿Se concilia físico-contable? ¿Hay trazabilidad de movimientos? ¿Se conocen activos críticos? | R11: Maestro de activos; inventario físico; conciliaciones; incidencias; ubicación; bajas/traslados. | S11: Crear modelo de inteligencia de activos con calidad de datos maestros, inventario, conciliación y trazabilidad del ciclo de vida.
A12: Activos fijos / Gestión de activos | B12: 3.3 Depreciación, impairments y valoración | C12: Evaluar el control financiero de depreciaciones, vidas útiles, deterioros y valoración de activos. | D12: Cálculos manuales o básicos, con revisiones limitadas de vidas útiles/deterioros. | E12: Reglas de depreciación configuradas parcialmente y análisis de impairment ad hoc. | F12: Políticas y reglas de depreciación/impairment documentadas y aplicadas recurrentemente. | G12: Modelo integrado con reporting, planificación de activos, KPIs operativos y revisiones estructuradas. | H12: Modelos IA detectan patrones de deterioro, anomalías de uso/coste y recomiendan revisión de vida útil, deterioro o mantenimiento. | I12: Mantenimiento predictivo de activos; Patrones históricos para predecir el rendimiento | M12: =IF(COUNTA(J12:L12)=0,"",ROUND(AVERAGE(J12:L12),2)) | N12: =IF(M12="","",IF(M12<1.5,"1 - Inicial",IF(M12<2.5,"2 - Estructurado",IF(M12<3.5,"3 - Estandarizado",IF(M12<4.5,"4 - Optimizado","5 - Avanzado/Referente"))))) | O12: =IF(M12="","",MAX(0,4-M12)) | P12: =IF(M12="","",IF(O12>=2,"Alta",IF(O12>=1,"Media","Baja"))) | Q12: ¿Se revisan vidas útiles? ¿Hay indicadores de deterioro? ¿Se conectan datos operativos con contabilidad? | R12: Cálculos depreciación; políticas contables; pruebas impairment; KPIs uso/mantenimiento; actas de revisión. | S12: Desarrollar modelo analítico para anticipar deterioros y revisar vida útil con datos financieros y operativos.
A13: Activos fijos / Gestión de activos | B13: 3.4 Bajas, desinversiones y control de CAPEX | C13: Evaluar el control de bajas, disposiciones, desinversiones y seguimiento del CAPEX asociado a activos. | D13: Bajas y disposiciones manuales, con bajo control de autorizaciones y resultados. | E13: Proceso básico de bajas y seguimiento CAPEX con revisiones manuales. | F13: Workflow estándar de baja/disposición y reporting de CAPEX con responsables definidos. | G13: Control integrado de CAPEX, activos, proyectos, aprobaciones, beneficios y desviaciones. | H13: IA prioriza decisiones de inversión/desinversión mediante business case, coste evitado, riesgo de activo y escenarios de rendimiento. | I13: Recomendaciones de acción a nivel de proyecto; Mantenimiento predictivo de activos | M13: =IF(COUNTA(J13:L13)=0,"",ROUND(AVERAGE(J13:L13),2)) | N13: =IF(M13="","",IF(M13<1.5,"1 - Inicial",IF(M13<2.5,"2 - Estructurado",IF(M13<3.5,"3 - Estandarizado",IF(M13<4.5,"4 - Optimizado","5 - Avanzado/Referente"))))) | O13: =IF(M13="","",MAX(0,4-M13)) | P13: =IF(M13="","",IF(O13>=2,"Alta",IF(O13>=1,"Media","Baja"))) | Q13: ¿Cómo se aprueban bajas? ¿Se mide ganancia/pérdida? ¿Se controla CAPEX? ¿Se vincula con business case? | R13: Bajas; autorizaciones; CAPEX; business cases; desviaciones; resultados de disposición. | S13: Implantar control del CAPEX y del ciclo de vida de los activos con analítica de coste evitado, riesgo y priorización de inversión y desinversión.
... A21: Contabilidad de proyectos | B21: 5.4 Forecast, cierre y análisis del proyecto | C21: Evaluar madurez de forecast, cierre económico y análisis post-mortem de proyectos. | D21: Forecast manual o inexistente, cierre tardío y sin análisis de lecciones aprendidas. | E21: Forecast básico de coste/margen y cierre con revisión manual. | F21: Forecast recurrente y cierre estructurado con análisis de desviaciones por proyecto. | G21: Forecast integrado coste-ingreso-caja, revisión de margen, lecciones aprendidas y acciones de mejora. | H21: La IA predice el rendimiento futuro del proyecto y genera escenarios, recomendaciones y un resumen ejecutivo de su salud financiera. | I21: Patrones históricos para predecir el rendimiento; Visión ejecutiva de la salud financiera; Recomendaciones de acción a nivel de proyecto | M21: =IF(COUNTA(J21:L21)=0,"",ROUND(AVERAGE(J21:L21),2)) | N21: =IF(M21="","",IF(M21<1.5,"1 - Inicial",IF(M21<2.5,"2 - Estructurado",IF(M21<3.5,"3 - Estandarizado",IF(M21<4.5,"4 - Optimizado","5 - Avanzado/Referente"))))) | O21: =IF(M21="","",MAX(0,4-M21)) | P21: =IF(M21="","",IF(O21>=2,"Alta",IF(O21>=1,"Media","Baja"))) | Q21: ¿Se actualiza forecast de proyectos? ¿Se analiza margen? ¿Se cierra con lecciones? ¿Se anticipan desviaciones? | R21: Forecast; margen; cash flow proyecto; cierre; post-mortem; acciones de mejora; reporting ejecutivo. | S21: Implantar previsión predictiva de proyectos con escenarios, alertas de margen y caja y recomendaciones de acción.

Sheet Resumen
A1: Capacidad | B1: Score Procesos | C1: Score Tecnología | D1: Score Organización | E1: Score Medio | F1: Gap vs objetivo | G1: Prioridad
A2: Source-to-Pay | B2: =IFERROR(ROUND(AVERAGEIF(Assessment!$A:$A,A2,Assessment!$J:$J),2),"") | C2: =IFERROR(ROUND(AVERAGEIF(Assessment!$A:$A,A2,Assessment!$K:$K),2),"") | D2: =IFERROR(ROUND(AVERAGEIF(Assessment!$A:$A,A2,Assessment!$L:$L),2),"") | E2: =IFERROR(ROUND(AVERAGEIF(Assessment!$A:$A,A2,Assessment!$M:$M),2),"") | F2: =IF(E2="","",MAX(0,4-E2)) | G2: =IF(E2="","",IF(F2>=2,"Alta",IF(F2>=1,"Media","Baja")))
A3: Order-to-Cash | B3: =IFERROR(ROUND(AVERAGEIF(Assessment!$A:$A,A3,Assessment!$J:$J),2),"") | C3: =IFERROR(ROUND(AVERAGEIF(Assessment!$A:$A,A3,Assessment!$K:$K),2),"") | D3: =IFERROR(ROUND(AVERAGEIF(Assessment!$A:$A,A3,Assessment!$L:$L),2),"") | E3: =IFERROR(ROUND(AVERAGEIF(Assessment!$A:$A,A3,Assessment!$M:$M),2),"") | F3: =IF(E3="","",MAX(0,4-E3)) | G3: =IF(E3="","",IF(F3>=2,"Alta",IF(F3>=1,"Media","Baja")))
A4: Activos fijos / Gestión de activos | B4: =IFERROR(ROUND(AVERAGEIF(Assessment!$A:$A,A4,Assessment!$J:$J),2),"") | C4: =IFERROR(ROUND(AVERAGEIF(Assessment!$A:$A,A4,Assessment!$K:$K),2),"") | D4: =IFERROR(ROUND(AVERAGEIF(Assessment!$A:$A,A4,Assessment!$L:$L),2),"") | E4: =IFERROR(ROUND(AVERAGEIF(Assessment!$A:$A,A4,Assessment!$M:$M),2),"") | F4: =IF(E4="","",MAX(0,4-E4)) | G4: =IF(E4="","",IF(F4>=2,"Alta",IF(F4>=1,"Media","Baja")))
A5: Informes operativos | B5: =IFERROR(ROUND(AVERAGEIF(Assessment!$A:$A,A5,Assessment!$J:$J),2),"") | C5: =IFERROR(ROUND(AVERAGEIF(Assessment!$A:$A,A5,Assessment!$K:$K),2),"") | D5: =IFERROR(ROUND(AVERAGEIF(Assessment!$A:$A,A5,Assessment!$L:$L),2),"") | E5: =IFERROR(ROUND(AVERAGEIF(Assessment!$A:$A,A5,Assessment!$M:$M),2),"") | F5: =IF(E5="","",MAX(0,4-E5)) | G5: =IF(E5="","",IF(F5>=2,"Alta",IF(F5>=1,"Media","Baja")))
A6: Contabilidad de proyectos | B6: =IFERROR(ROUND(AVERAGEIF(Assessment!$A:$A,A6,Assessment!$J:$J),2),"") | C6: =IFERROR(ROUND(AVERAGEIF(Assessment!$A:$A,A6,Assessment!$K:$K),2),"") | D6: =IFERROR(ROUND(AVERAGEIF(Assessment!$A:$A,A6,Assessment!$L:$L),2),"") | E6: =IFERROR(ROUND(AVERAGEIF(Assessment!$A:$A,A6,Assessment!$M:$M),2),"") | F6: =IF(E6="","",MAX(0,4-E6)) | G6: =IF(E6="","",IF(F6>=2,"Alta",IF(F6>=1,"Media","Baja")))
A8: Score global dominio | B8: =IFERROR(ROUND(AVERAGE(B2:B6),2),"") | C8: =IFERROR(ROUND(AVERAGE(C2:C6),2),"") | D8: =IFERROR(ROUND(AVERAGE(D2:D6),2),"") | E8: =IFERROR(ROUND(AVERAGE(E2:E6),2),"") | F8: =IFERROR(ROUND(AVERAGE(F2:F6),2),"") | G8: =IF(E8="","",IF(F8>=2,"Alta",IF(F8>=1,"Media","Baja")))

Sheet Heatmap
A1: Capacidad | B1: Subcapacidad | C1: Procesos | D1: Tecnología | E1: Organización | F1: Score medio | G1: Gap | H1: Prioridad | I1: Casos AI
A2: =Assessment!A2 -> Source-to-Pay | B2: =Assessment!B2 -> 1.1 Estrategia de compras, categorías y demanda | C2: =Assessment!J2 -> 0 | D2: =Assessment!K2 -> 0 | E2: =Assessment!L2 -> 0 | F2: =Assessment!M2 | G2: =Assessment!O2 | H2: =Assessment!P2 | I2: =Assessment!I2 -> Using data from contract management system, forecast monthly expense for all third-party contracts; Resilient logistics and planning
A3: =Assessment!A3 -> Source-to-Pay | B3: =Assessment!B3 -> 1.2 Selección, evaluación y gestión de proveedores | C3: =Assessment!J3 -> 0 | D3: =Assessment!K3 -> 0 | E3: =Assessment!L3 -> 0 | F3: =Assessment!M3 | G3: =Assessment!O3 | H3: =Assessment!P3 | I3: =Assessment!I3 -> Resilient logistics and planning; Supplier assessment AI; Drafting contracts and SoWs
A4: =Assessment!A4 -> Source-to-Pay | B4: =Assessment!B4 -> 1.3 Gestión contractual, RFPs y SoWs | C4: =Assessment!J4 -> 0 | D4: =Assessment!K4 -> 0 | E4: =Assessment!L4 -> 0 | F4: =Assessment!M4 | G4: =Assessment!O4 | H4: =Assessment!P4 | I4: =Assessment!I4 -> Drafting contracts and SoWs; AI-powered RFP and knowledge assistant; Using data from contract management system forecast monthly expense
A5: =Assessment!A5 -> Source-to-Pay | B5: =Assessment!B5 -> 1.4 Orden de compra, recepción y aprobación | C5: =Assessment!J5 -> 0 | D5: =Assessment!K5 -> 0 | E5: =Assessment!L5 -> 0 | F5: =Assessment!M5 | G5: =Assessment!O5 | H5: =Assessment!P5 | I5: =Assessment!I5 -> Recommend most optimal payment timing; Proactive defect resolution recommendations; Guided adaptable workflows for master data record changes
A6: =Assessment!A6 -> Order-to-Cash | B6: =Assessment!B6 -> 2.1 Gestión de pedidos, contratos y condiciones comerciales | C6: =Assessment!J6 -> 0 | D6: =Assessment!K6 -> 0 | E6: =Assessment!L6 -> 0 | F6: =Assessment!M6 | G6: =Assessment!O6 | H6: =Assessment!P6 | I6: =Assessment!I6 -> Read customer contracts and identify performance obligations; Identify & proactively correct revenue leakage; AI assistant for vehicle buying and leasing
A7: =Assessment!A7 -> Order-to-Cash | B7: =Assessment!B7 -> 2.2 Facturación y emisión de documentos | C7: =Assessment!J7 -> 0 | D7: =Assessment!K7 -> 0 | E7: =Assessment!L7 -> 0 | F7: =Assessment!M7 | G7: =Assessment!O7 | H7: =Assessment!P7 | I7: =Assessment!I7 -> Automated invoice error detection & correction; Generate customized invoices for nonstandard customer orders
A8: =Assessment!A8 -> Order-to-Cash | B8: =Assessment!B8 -> 2.3 Cobros, aplicación de pagos y gestión de disputas | C8: =Assessment!J8 -> 0 | D8: =Assessment!K8 -> 0 | E8: =Assessment!L8 -> 0 | F8: =Assessment!M8 | G8: =Assessment!O8 | H8: =Assessment!P8 | I8: =Assessment!I8 -> Facilitate payment collection to identify collections gaps and automate outreach; Recommend optimal payment terms to improve DSO; Denial appeal letters
A9: =Assessment!A9 -> Order-to-Cash | B9: =Assessment!B9 -> 2.4 Crédito, riesgo cliente y control de exposición | C9: =Assessment!J9 -> 0 | D9: =Assessment!K9 -> 0 | E9: =Assessment!L9 -> 0 | F9: =Assessment!M9 | G9: =Assessment!O9 | H9: =Assessment!P9 | I9: =Assessment!I9 -> AI agents for credit underwriting; Predicts late payments or defaults; Recommend optimal payment terms to improve DSO
A10: =Assessment!A10 -> Activos fijos / Gestión de activos | B10: =Assessment!B10 -> 3.1 Alta, capitalización y clasificación de activos | C10: =Assessment!J10 -> 0 | D10: =Assessment!K10 -> 0 | E10: =Assessment!L10 -> 0 | F10: =Assessment!M10 | G10: =Assessment!O10 | H10: =Assessment!P10 | I10: =Assessment!I10 -> Identify expense classification errors; Generate metadata documentation; Guided adaptable workflows for master data record changes
A11: =Assessment!A11 -> Activos fijos / Gestión de activos | B11: =Assessment!B11 -> 3.2 Inventario, localización y trazabilidad de activos | C11: =Assessment!J11 -> 0 | D11: =Assessment!K11 -> 0 | E11: =Assessment!L11 -> 0 | F11: =Assessment!M11 | G11: =Assessment!O11 | H11: =Assessment!P11 | I11: =Assessment!I11 -> Identify inconsistencies in master data records; AI-powered archive access and extraction; Autonomous drone-based infrastructure inspection
A12: =Assessment!A12 -> Activos fijos / Gestión de activos | B12: =Assessment!B12 -> 3.3 Depreciación, impairments y valoración | C12: =Assessment!J12 -> 0 | D12: =Assessment!K12 -> 0 | E12: =Assessment!L12 -> 0 | F12: =Assessment!M12 | G12: =Assessment!O12 | H12: =Assessment!P12 | I12: =Assessment!I12 -> AI-driven predictive maintenance; Identify past data patterns to predict and improve future financial performance
A13: =Assessment!A13 -> Activos fijos / Gestión de activos | B13: =Assessment!B13 -> 3.4 Bajas, desinversiones y control de CAPEX | C13: =Assessment!J13 -> 0 | D13: =Assessment!K13 -> 0 | E13: =Assessment!L13 -> 0 | F13: =Assessment!M13 | G13: =Assessment!O13 | H13: =Assessment!P13 | I13: =Assessment!I13 -> Project-level recommendations; AI-driven predictive maintenance; Autonomous drone-based infrastructure inspection
... A21: =Assessment!A21 -> Contabilidad de proyectos | B21: =Assessment!B21 -> 5.4 Forecast, cierre y análisis del proyecto | C21: =Assessment!J21 -> 0 | D21: =Assessment!K21 -> 0 | E21: =Assessment!L21 -> 0 | F21: =Assessment!M21 | G21: =Assessment!O21 | H21: =Assessment!P21 | I21: =Assessment!I21 -> Identify past data patterns to predict and improve future financial performance; Generate executive level overview of company financial health; Project-level recommendations

Sheet Roadmap
A1: Capacidad | B1: Subcapacidad | C1: Gap | D1: Prioridad | E1: Iniciativa sugerida | F1: Casos AI asociados | G1: Oleada | H1: Owner | I1: Estado | J1: Comentarios
A2: =Assessment!A2 -> Source-to-Pay | B2: =Assessment!B2 -> 1.1 Estrategia de compras, categorías y demanda | C2: =Assessment!O2 | D2: =Assessment!P2 | E2: =Assessment!S2 -> Implantar planificación de demanda de compras por categoría con previsión de gasto contractual y conexión con presupuesto. | F2: =Assessment!I2 | G2: =IF(D2="Alta","Oleada 1",IF(D2="Media","Oleada 2","Oleada 3")) -> Oleada 3 | I2: No iniciado
A3: =Assessment!A3 -> Source-to-Pay | B3: =Assessment!B3 -> 1.2 Selección, evaluación y gestión de proveedores | C3: =Assessment!O3 | D3: =Assessment!P3 | E3: =Assessment!S3 -> Crear modelo de inteligencia de proveedores con indicadores de desempeño, riesgo, cumplimiento y recomendaciones de aprovisionamiento. | F3: =Assessment!I3 | G3: =IF(D3="Alta","Oleada 1",IF(D3="Media","Oleada 2","Oleada 3")) -> Oleada 3 | I3: No iniciado
A4: =Assessment!A4 -> Source-to-Pay | B4: =Assessment!B4 -> 1.3 Gestión contractual, RFPs y SoWs | C4: =Assessment!O4 | D4: =Assessment!P4 | E4: =Assessment!S4 -> Implantar asistente contractual AI para generación, revisión y explotación financiera de contratos y SoWs. | F4: =Assessment!I4 | G4: =IF(D4="Alta","Oleada 1",IF(D4="Media","Oleada 2","Oleada 3")) -> Oleada 3 | I4: No iniciado
A5: =Assessment!A5 -> Source-to-Pay | B5: =Assessment!B5 -> 1.4 Orden de compra, recepción y aprobación | C5: =Assessment!O5 | D5: =Assessment!P5 | E5: =Assessment!S5 -> Digitalizar el flujo de solicitud, pedido y recepción con controles automáticos, excepciones y recomendaciones de aprobación y pago. | F5: =Assessment!I5 | G5: =IF(D5="Alta","Oleada 1",IF(D5="Media","Oleada 2","Oleada 3")) -> Oleada 3 | I5: No iniciado
A6: =Assessment!A6 -> Order-to-Cash | B6: =Assessment!B6 -> 2.1 Gestión de pedidos, contratos y condiciones comerciales | C6: =Assessment!O6 | D6: =Assessment!P6 | E6: =Assessment!S6 -> Crear controles automáticos de pedido/contrato/precio con detección de condiciones atípicas y fugas de ingresos. | F6: =Assessment!I6 | G6: =IF(D6="Alta","Oleada 1",IF(D6="Media","Oleada 2","Oleada 3")) -> Oleada 3 | I6: No iniciado
A7: =Assessment!A7 -> Order-to-Cash | B7: =Assessment!B7 -> 2.2 Facturación y emisión de documentos | C7: =Assessment!O7 | D7: =Assessment!P7 | E7: =Assessment!S7 -> Implantar motor AI de validación y corrección preventiva de facturas antes de emisión. | F7: =Assessment!I7 | G7: =IF(D7="Alta","Oleada 1",IF(D7="Media","Oleada 2","Oleada 3")) -> Oleada 3 | I7: No iniciado
A8: =Assessment!A8 -> Order-to-Cash | B8: =Assessment!B8 -> 2.3 Cobros, aplicación de pagos y gestión de disputas | C8: =Assessment!O8 | D8: =Assessment!P8 | E8: =Assessment!S8 -> Desplegar asistente inteligente de gestión de cobros con priorización, contacto automatizado con clientes y recomendaciones de condiciones. | F8: =Assessment!I8 | G8: =IF(D8="Alta","Oleada 1",IF(D8="Media","Oleada 2","Oleada 3")) -> Oleada 3 | I8: No iniciado
A9: =Assessment!A9 -> Order-to-Cash | B9: =Assessment!B9 -> 2.4 Crédito, riesgo cliente y control de exposición | C9: =Assessment!O9 | D9: =Assessment!P9 | E9: =Assessment!S9 -> Construir modelo predictivo de riesgo cliente con recomendaciones de límite, términos y acciones preventivas. | F9: =Assessment!I9 | G9: =IF(D9="Alta","Oleada 1",IF(D9="Media","Oleada 2","Oleada 3")) -> Oleada 3 | I9: No iniciado
A10: =Assessment!A10 -> Activos fijos / Gestión de activos | B10: =Assessment!B10 -> 3.1 Alta, capitalización y clasificación de activos | C10: =Assessment!O10 | D10: =Assessment!P10 | E10: =Assessment!S10 -> Implantar clasificación asistida CAPEX/OPEX y flujo de alta de activos con controles de soporte documental. | F10: =Assessment!I10 | G10: =IF(D10="Alta","Oleada 1",IF(D10="Media","Oleada 2","Oleada 3")) -> Oleada 3 | I10: No iniciado
A11: =Assessment!A11 -> Activos fijos / Gestión de activos | B11: =Assessment!B11 -> 3.2 Inventario, localización y trazabilidad de activos | C11: =Assessment!O11 | D11: =Assessment!P11 | E11: =Assessment!S11 -> Crear modelo de inteligencia de activos con calidad de datos maestros, inventario, conciliación y trazabilidad del ciclo de vida. | F11: =Assessment!I11 | G11: =IF(D11="Alta","Oleada 1",IF(D11="Media","Oleada 2","Oleada 3")) -> Oleada 3 | I11: No iniciado
A12: =Assessment!A12 -> Activos fijos / Gestión de activos | B12: =Assessment!B12 -> 3.3 Depreciación, impairments y valoración | C12: =Assessment!O12 | D12: =Assessment!P12 | E12: =Assessment!S12 -> Desarrollar modelo analítico para anticipar deterioros y revisar vida útil con datos financieros y operativos. | F12: =Assessment!I12 | G12: =IF(D12="Alta","Oleada 1",IF(D12="Media","Oleada 2","Oleada 3")) -> Oleada 3 | I12: No iniciado
A13: =Assessment!A13 -> Activos fijos / Gestión de activos | B13: =Assessment!B13 -> 3.4 Bajas, desinversiones y control de CAPEX | C13: =Assessment!O13 | D13: =Assessment!P13 | E13: =Assessment!S13 -> Implantar control del CAPEX y del ciclo de vida de los activos con analítica de coste evitado, riesgo y priorización de inversión y desinversión. | F13: =Assessment!I13 | G13: =IF(D13="Alta","Oleada 1",IF(D13="Media","Oleada 2","Oleada 3")) -> Oleada 3 | I13: No iniciado
... A21: =Assessment!A21 -> Contabilidad de proyectos | B21: =Assessment!B21 -> 5.4 Forecast, cierre y análisis del proyecto | C21: =Assessment!O21 | D21: =Assessment!P21 | E21: =Assessment!S21 -> Implantar previsión predictiva de proyectos con escenarios, alertas de margen y caja y recomendaciones de acción. | F21: =Assessment!I21 | G21: =IF(D21="Alta","Oleada 1",IF(D21="Media","Oleada 2","Oleada 3")) -> Oleada 3 | I21: No iniciado

Sheet AI Overlay
A1: Capacidad | B1: Subcapacidad | C1: Casos de uso AI asociados | D1: Aplicación en nivel avanzado | E1: Fuente
A2: Source-to-Pay | B2: 1.1 Estrategia de compras, categorías y demanda | C2: Previsión del gasto contratado con terceros; Planificación logística resiliente | D2: Planificación predictiva del gasto y la demanda de terceros a partir de contratos, histórico y señales externas, con recomendación de aprovisionamiento y de calendario. | E2: F3M_AI_Mapping_Consolidado_v1.xlsx
A3: Source-to-Pay | B3: 1.2 Selección, evaluación y gestión de proveedores | C3: Planificación logística resiliente; Evaluación de proveedores con IA; Redacción de contratos y pliegos; Insights sobre el dato de proveedor | D3: Motor de IA para evaluar proveedores y el riesgo de la cadena de suministro, con recomendación de selección y de negociación según desempeño, riesgo y contexto externo. | E3: F3M_AI_Mapping_Consolidado_v1.xlsx
A4: Source-to-Pay | B4: 1.3 Gestión contractual, RFPs y SoWs | C4: Redacción de contratos y pliegos; Asistente de RFP y de conocimiento comercial; Previsión del gasto contratado con terceros | D4: Asistente IA para generar RFP, contratos y SoW, extraer cláusulas, analizar riesgos y recomendar condiciones financieras/comerciales. | E4: F3M_AI_Mapping_Consolidado_v1.xlsx
A5: Source-to-Pay | B5: 1.4 Orden de compra, recepción y aprobación | C5: Momento óptimo de pago a proveedores; Recomendaciones de resolución de incidencias; Flujos guiados de cambio en datos maestros; Detección de facturas duplicadas | D5: IA recomienda momento óptimo de pagos/compras, detecta excepciones operativas y prioriza aprobaciones según impacto en caja, contrato y riesgo. | E5: F3M_AI_Mapping_Consolidado_v1.xlsx
A6: Order-to-Cash | B6: 2.1 Gestión de pedidos, contratos y condiciones comerciales | C6: Lectura de contratos y obligaciones de desempeño; Detección de fugas de ingresos | D6: Asistente IA analiza contratos/pedidos, valida obligaciones y condiciones comerciales, y recomienda acciones para evitar errores, fuga de ingresos o disputas. | E6: F3M_AI_Mapping_Consolidado_v1.xlsx
A7: Order-to-Cash | B7: 2.2 Facturación y emisión de documentos | C7: Detección y corrección de errores en facturas; Facturación de pedidos no estándar | D7: Detección/corrección IA de errores de factura y generación de facturas personalizadas para pedidos no estándar, con validación fiscal/contable. | E7: F3M_AI_Mapping_Consolidado_v1.xlsx
A8: Order-to-Cash | B8: 2.3 Cobros, aplicación de pagos y gestión de disputas | C8: Gestión asistida del recobro; Condiciones de pago óptimas para el DSO; Redacción de recursos ante denegaciones; Asistente financiero para el cliente | D8: Un asistente de IA identifica las brechas de cobro, automatiza el contacto con el cliente, recomienda las condiciones de pago que mejoran el DSO y apoya la recuperación de ingresos y la gestión de disputas. | E8: F3M_AI_Mapping_Consolidado_v1.xlsx
A9: Order-to-Cash | B9: 2.4 Crédito, riesgo cliente y control de exposición | C9: Agentes de IA para análisis de riesgo crediticio; Predicción de retraso e impago; Condiciones de pago óptimas para el DSO | D9: Puntuación dinámica con IA del cliente y del riesgo de cobro, con alertas tempranas y recomendación de bloqueo o liberación y de condiciones comerciales. | E9: F3M_AI_Mapping_Consolidado_v1.xlsx
A10: Activos fijos / Gestión de activos | B10: 3.1 Alta, capitalización y clasificación de activos | C10: Detección de errores de clasificación de gasto; Generación de documentación de metadatos; Flujos guiados de cambio en datos maestros | D10: IA ayuda a clasificar gastos vs activos, detectar errores de codificación y generar metadatos/documentación de activos. | E10: F3M_AI_Mapping_Consolidado_v1.xlsx
A11: Activos fijos / Gestión de activos | B11: 3.2 Inventario, localización y trazabilidad de activos | C11: Detección de inconsistencias en datos maestros; Acceso y extracción documental | D11: La IA, apoyada en sensorización digital, detecta inconsistencias y anomalías de activos y genera alertas sobre los activos críticos o no conciliados. | E11: F3M_AI_Mapping_Consolidado_v1.xlsx
A12: Activos fijos / Gestión de activos | B12: 3.3 Depreciación, impairments y valoración | C12: Mantenimiento predictivo de activos; Patrones históricos para predecir el rendimiento | D12: Modelos IA detectan patrones de deterioro, anomalías de uso/coste y recomiendan revisión de vida útil, deterioro o mantenimiento. | E12: F3M_AI_Mapping_Consolidado_v1.xlsx
... A21: Contabilidad de proyectos | B21: 5.4 Forecast, cierre y análisis del proyecto | C21: Patrones históricos para predecir el rendimiento; Visión ejecutiva de la salud financiera; Recomendaciones de acción a nivel de proyecto | D21: La IA predice el rendimiento futuro del proyecto y genera escenarios, recomendaciones y un resumen ejecutivo de su salud financiera. | E21: F3M_AI_Mapping_Consolidado_v1.xlsx

Sheet Guias scoring
A1: GUÍAS DE SCORING F3M
A3: PROCESOS
A4: Nivel 1 - Inicial: Proceso inexistente, manual o ad hoc.
A5: Nivel 2 - Estructurado: Proceso parcial, definido con variabilidad y dependencias manuales.
A6: Nivel 3 - Estandarizado: Proceso documentado, homogéneo y repetible.
A7: Nivel 4 - Optimizado: Proceso medido, eficiente, con controles y mejora continua.
A8: Nivel 5 - Avanzado: Proceso integrado end-to-end, orientado a decisión y habilitado por automatización/AI cuando aplique.
A10: TECNOLOGÍA
A11: Nivel 1 - Inicial: Excel/manual, sin integración.
A12: Nivel 2 - Estructurado: Herramientas parciales o locales, con baja integración.
A13: Nivel 3 - Estandarizado: Herramienta corporativa y reglas definidas.
A14: Nivel 4 - Optimizado: Integración end-to-end, automatización y controles tecnológicos.
... A28: - No sobrevalorar la tecnología si el proceso o la adopción no están maduros.

Sheet Instrucciones
A1: F3M - Transaccional | Assessment-ready con AI
A2: Uso | B2: Puntuar cada subcapacidad en Procesos, Tecnología y Organización usando escala 1-5.
A3: Dominio | B3: Transacciones: Source-to-Pay, Order-to-Cash, Activos fijos / Gestión de activos, Informes operativos y Contabilidad de proyectos.
A4: Nivel avanzado | B4: Los niveles 5 incorporan casos de uso AI del fichero consolidado F3M_AI_Mapping_Consolidado_v1.xlsx; en capacidades con menor cobertura directa se han usado casos del consolidado por analogía funcional.
A5: Objetivo de madurez | B5: El gap se calcula frente a Nivel 4 - Optimizado.
A6: Pestañas | B6: Assessment, Resumen, Heatmap, Roadmap, AI Overlay, Guias scoring e Instrucciones.
