Workbook

Sheet Assessment
A1: Capacidad | B1: Subcapacidad | C1: Objetivo de evaluación | D1: Nivel 1 - Inicial | E1: Nivel 2 - Estructurado | F1: Nivel 3 - Estandarizado | G1: Nivel 4 - Optimizado | H1: Nivel 5 - Avanzado/Referente | I1: Casos de uso AI asociados | J1: Score Procesos | K1: Score Tecnología | L1: Score Organización | M1: Score Medio | N1: Nivel resultante | O1: Gap vs objetivo | P1: Prioridad | Q1: Preguntas clave | R1: Evidencias | S1: Iniciativa sugerida | T1: Comentarios / hallazgos
A2: Financiación I+D | B2: 1.1 Gobierno y portfolio de iniciativas de I+D | C2: Evaluar si existe un marco formal para identificar, aprobar, priorizar y gobernar iniciativas de I+D desde una perspectiva financiera y de creación de valor. | D2: Iniciativas de I+D gestionadas de forma aislada, con baja visibilidad financiera, criterios de aprobación no homogéneos y dependencia elevada de sponsors individuales. | E2: Existe un inventario básico de iniciativas y criterios financieros parciales, aunque la priorización y el seguimiento son heterogéneos entre áreas o unidades. | F2: Portfolio de I+D definido, con ownership, criterios de aprobación, presupuestos, métricas económicas y proceso periódico de revisión. | G2: Gobierno integrado del portfolio de I+D con estrategia, presupuesto, riesgos, capacidad de ejecución, beneficios esperados y reasignación periódica de recursos. | H2: Cartera de innovación dinámica y basada en IA, con priorización por escenarios, señales de mercado, probabilidad de éxito y ROI esperado, y recomendación de asignación de capital. | I2: Diseño de producto orquestado por IA; Ensayos clínicos más inteligentes; Descubrimiento autónomo de fármacos | M2: =IF(COUNT(J2:L2)=0,"",ROUND(AVERAGE(J2:L2),0)) | N2: =IF(M2="","",CHOOSE(M2,"1 - Inicial","2 - Estructurado","3 - Estandarizado","4 - Optimizado","5 - Avanzado/Referente")) | O2: =IF(M2="","",MAX(0,4-M2)) | P2: =IF(O2="","",IF(O2>=3,"Alta",IF(O2=2,"Media",IF(O2=1,"Media","Baja")))) | Q2: ¿Existe portfolio formal de iniciativas de I+D? ¿Se priorizan iniciativas con criterios financieros y estratégicos? ¿Hay owners y governance de aprobación? ¿Se revisa periódicamente la continuidad de las iniciativas? | R2: Portfolio de I+D; criterios de priorización; actas de comité; business cases; presupuesto por iniciativa; matriz de ownership. | S2: Diseñar modelo de gobierno de la cartera de I+D con criterios de valor, riesgo, alineamiento estratégico, financiación y seguimiento periódico.
A3: Financiación I+D | B3: 1.2 Planificación y control económico de proyectos de I+D | C3: Evaluar la capacidad para planificar, presupuestar, forecastar y controlar costes, inversiones y desviaciones de proyectos de I+D. | D3: Costes de I+D controlados de forma manual y retrospectiva, con baja conexión entre presupuesto, ejecución y avance de los proyectos. | E3: Presupuestos básicos por proyecto, con seguimiento periódico limitado y análisis manual de desviaciones relevantes. | F3: Planificación económica estructurada por proyecto, fase, hito y naturaleza de coste, con reporting recurrente y análisis de desviaciones. | G3: Control integrado de presupuesto, forecast, avance técnico, recursos, riesgos y beneficios esperados, con alertas y acciones correctivas. | H3: Planificación predictiva de costes y avance de I+D, con simulación de escenarios, detección temprana de desviaciones y recomendaciones sobre continuidad, aceleración o cancelación. | I3: Diseño de producto orquestado por IA; Ensayos clínicos más inteligentes; Descubrimiento autónomo de fármacos | M3: =IF(COUNT(J3:L3)=0,"",ROUND(AVERAGE(J3:L3),0)) | N3: =IF(M3="","",CHOOSE(M3,"1 - Inicial","2 - Estructurado","3 - Estandarizado","4 - Optimizado","5 - Avanzado/Referente")) | O3: =IF(M3="","",MAX(0,4-M3)) | P3: =IF(O3="","",IF(O3>=3,"Alta",IF(O3=2,"Media",IF(O3=1,"Media","Baja")))) | Q3: ¿Se presupuestan proyectos por fase e hito? ¿Se actualiza forecast económico de I+D? ¿Se analiza desviación por driver? ¿Se conectan costes con avance y beneficios esperados? | R3: Presupuesto de I+D; forecast por proyecto; informes de desviaciones; hitos técnicos; costes reales; actas de seguimiento. | S3: Implantar modelo de control económico de proyectos de I+D con presupuesto, previsión, hitos, desviaciones, riesgos y acciones correctivas.
A4: Financiación I+D | B4: 1.3 Financiación, subvenciones e incentivos de I+D | C4: Evaluar si la organización identifica, captura y gestiona fuentes de financiación, subvenciones e incentivos aplicables a actividades de I+D. | D4: Oportunidades de financiación o incentivos identificadas de forma reactiva, con documentación dispersa y baja trazabilidad. | E4: Se gestionan algunas ayudas o incentivos relevantes, aunque la identificación, justificación y seguimiento dependen de esfuerzos manuales. | F4: Proceso definido para identificar, evaluar, solicitar y justificar financiación e incentivos de I+D, con responsabilidades claras. | G4: Gestión integrada de funding con portfolio, presupuesto, contabilidad, fiscalidad, reporting y evidencias requeridas por organismos financiadores. | H4: Motor inteligente de identificación y optimización de incentivos, con cribado normativo, elegibilidad predictiva, generación asistida de documentación y alertas de cumplimiento. | I4: Cumplimiento regulatorio automatizado; Interpretación de normativa financiera; Diseño de producto orquestado por IA; Determinación de elegibilidad para incentivos | M4: =IF(COUNT(J4:L4)=0,"",ROUND(AVERAGE(J4:L4),0)) | N4: =IF(M4="","",CHOOSE(M4,"1 - Inicial","2 - Estructurado","3 - Estandarizado","4 - Optimizado","5 - Avanzado/Referente")) | O4: =IF(M4="","",MAX(0,4-M4)) | P4: =IF(O4="","",IF(O4>=3,"Alta",IF(O4=2,"Media",IF(O4=1,"Media","Baja")))) | Q4: ¿Se monitorizan fuentes de financiación e incentivos? ¿Existe proceso de elegibilidad y solicitud? ¿Se documentan evidencias para justificación? ¿Se integran incentivos en forecast y reporting? | R4: Mapa de incentivos; expedientes de subvención; justificaciones; documentación técnica; registros contables; calendario de obligaciones. | S4: Crear proceso estructurado de financiación e incentivos de I+D con análisis de elegibilidad, evidencias, flujo de aprobación y seguimiento financiero.
A5: Financiación I+D | B5: 1.4 Medición de valor y retorno de la innovación | C5: Evaluar si la organización mide el retorno financiero, estratégico y operativo de las inversiones de I+D a lo largo del ciclo de vida. | D5: No existe medición sistemática del retorno de I+D; el seguimiento se centra en gasto ejecutado o hitos técnicos. | E5: Se miden beneficios de algunas iniciativas, pero con criterios variables y baja conexión con decisiones de portfolio. | F5: KPIs de valor definidos para I+D, con seguimiento periódico de avance, coste, beneficios, riesgos y grado de consecución. | G5: Modelo integrado de value tracking conectado con portfolio, business cases, beneficios reales, aprendizaje y reasignación de recursos. | H5: Medición avanzada de valor con modelos predictivos, análisis de contribución, escenarios de monetización y recomendaciones de inversión/desinversión en innovación. | I5: Descubrimiento autónomo de fármacos; Diseño de producto orquestado por IA; Recomendaciones de acción a nivel de proyecto | M5: =IF(COUNT(J5:L5)=0,"",ROUND(AVERAGE(J5:L5),0)) | N5: =IF(M5="","",CHOOSE(M5,"1 - Inicial","2 - Estructurado","3 - Estandarizado","4 - Optimizado","5 - Avanzado/Referente")) | O5: =IF(M5="","",MAX(0,4-M5)) | P5: =IF(O5="","",IF(O5>=3,"Alta",IF(O5=2,"Media",IF(O5=1,"Media","Baja")))) | Q5: ¿Se mide ROI de iniciativas de I+D? ¿Existen KPIs de valor financiero y estratégico? ¿Se comparan beneficios reales vs esperados? ¿Se usan aprendizajes para futuras decisiones? | R5: KPIs de innovación; benefit tracking; business cases; informes post-implementación; decisiones de portfolio; lecciones aprendidas. | S5: Definir modelo de medición de valor de I+D con KPIs, beneficios esperados y reales, responsables, revisión de la cartera y aprendizaje recurrente.
A6: Financiación de ventas comerciales | B6: 2.1 Gobierno financiero de propuestas y condiciones comerciales | C6: Evaluar si existe un marco financiero para gobernar propuestas, ofertas, condiciones comerciales, descuentos y excepciones. | D6: Condiciones comerciales definidas caso a caso, con baja implicación financiera y controles limitados sobre descuentos, riesgos o márgenes. | E6: Políticas comerciales básicas y revisión financiera para operaciones relevantes, aunque con excepciones frecuentes y trazabilidad parcial. | F6: Modelo de gobierno comercial-financiero con políticas, umbrales, aprobaciones, criterios de margen y control de excepciones. | G6: Gobierno integrado con CRM, pricing, crédito, contratos, rentabilidad y forecast comercial, con workflow y reporting de cumplimiento. | H6: Asistente IA para propuestas comerciales que recomienda condiciones, identifica riesgos, estima rentabilidad y guía aprobaciones según margen, cliente y probabilidad de conversión. | I6: Asistente de RFP y de conocimiento comercial; Operaciones comerciales inteligentes | M6: =IF(COUNT(J6:L6)=0,"",ROUND(AVERAGE(J6:L6),0)) | N6: =IF(M6="","",CHOOSE(M6,"1 - Inicial","2 - Estructurado","3 - Estandarizado","4 - Optimizado","5 - Avanzado/Referente")) | O6: =IF(M6="","",MAX(0,4-M6)) | P6: =IF(O6="","",IF(O6>=3,"Alta",IF(O6=2,"Media",IF(O6=1,"Media","Baja")))) | Q6: ¿Existen políticas financieras para ofertas y descuentos? ¿Se aprueban excepciones con workflow? ¿Se calcula margen esperado antes de ofertar? ¿Se conectan condiciones comerciales con contrato y forecast? | R6: Políticas comerciales; matriz de descuentos; aprobaciones; CRM; ofertas; contratos; análisis de margen por oportunidad. | S6: Diseñar gobierno financiero de propuestas comerciales con reglas de margen, descuentos, riesgos, aprobaciones y trazabilidad de principio a fin.
A7: Financiación de ventas comerciales | B7: 2.2 Evaluación financiera de oportunidades, RFPs y ofertas | C7: Evaluar la capacidad para analizar oportunidades comerciales, RFPs y ofertas desde una perspectiva de valor, rentabilidad, riesgo y capacidad de entrega. | D7: Evaluación financiera limitada o tardía, con foco en ingresos esperados y baja consideración de costes, riesgos o capacidad. | E7: Análisis financiero básico en oportunidades relevantes, con plantillas parciales y dependencia de analistas o equipos comerciales. | F7: Modelo estándar de evaluación de oportunidades con ingresos, costes, margen, riesgos, condiciones, capacidad y probabilidad de éxito. | G7: Evaluación integrada con pipeline, pricing, capacidad operativa, riesgos contractuales, forecast y priorización comercial. | H7: Asistente de IA para RFP que resume los requisitos, estima la rentabilidad esperada, identifica riesgos, propone respuestas y prioriza oportunidades por valor ajustado a probabilidad y riesgo. | I7: Asistente de RFP y de conocimiento comercial; Operaciones comerciales inteligentes; Personalización de ventas y marketing | M7: =IF(COUNT(J7:L7)=0,"",ROUND(AVERAGE(J7:L7),0)) | N7: =IF(M7="","",CHOOSE(M7,"1 - Inicial","2 - Estructurado","3 - Estandarizado","4 - Optimizado","5 - Avanzado/Referente")) | O7: =IF(M7="","",MAX(0,4-M7)) | P7: =IF(O7="","",IF(O7>=3,"Alta",IF(O7=2,"Media",IF(O7=1,"Media","Baja")))) | Q7: ¿Se evalúan oportunidades con criterios homogéneos? ¿Se cuantifica coste de servir y margen esperado? ¿Se incorpora riesgo contractual/comercial? ¿Se prioriza el pipeline por valor ajustado? | R7: RFPs; plantillas de análisis; pipeline comercial; modelos de margen; actas de bid/no-bid; aprobaciones de ofertas. | S7: Implantar modelo de evaluación financiera de oportunidades y RFPs con análisis económico, riesgos, capacidad, probabilidad y priorización de la cartera comercial.
A8: Financiación de ventas comerciales | B8: 2.3 Gestión de riesgos comerciales y exposición financiera | C8: Evaluar el control de riesgos financieros asociados a actividad comercial: crédito, concentración, condiciones, contratos, penalizaciones y exposición. | D8: Riesgos comerciales gestionados reactivamente, con baja conexión entre ventas, finanzas, crédito y contratos. | E8: Se revisan riesgos en operaciones relevantes, aunque con criterios no homogéneos y análisis manual de exposición. | F8: Modelo de riesgo comercial definido con criterios de crédito, exposición, términos, concentración, rentabilidad y aprobación. | G8: Riesgo comercial integrado con CRM, contratos, O2C, pricing, margen, cash y límites de exposición, con alertas y seguimiento. | H8: Puntuación predictiva del riesgo comercial y de la exposición, con recomendación de condiciones, garantías, límites, precio y acciones preventivas por cliente u oportunidad. | I8: Agentes de IA para análisis de riesgo crediticio; Condiciones de pago óptimas para el DSO; Operaciones comerciales inteligentes | M8: =IF(COUNT(J8:L8)=0,"",ROUND(AVERAGE(J8:L8),0)) | N8: =IF(M8="","",CHOOSE(M8,"1 - Inicial","2 - Estructurado","3 - Estandarizado","4 - Optimizado","5 - Avanzado/Referente")) | O8: =IF(M8="","",MAX(0,4-M8)) | P8: =IF(O8="","",IF(O8>=3,"Alta",IF(O8=2,"Media",IF(O8=1,"Media","Baja")))) | Q8: ¿Se evalúa riesgo financiero de clientes y ofertas? ¿Existen límites y condiciones por perfil de riesgo? ¿Se monitoriza exposición comercial? ¿Se conectan riesgos con pricing y aprobación? | R8: Política de crédito; límites; exposición por cliente; contratos; términos comerciales; aging; aprobaciones de riesgo. | S8: Construir modelo de riesgo comercial financiero con puntuación de riesgo, límites, condiciones, exposición, alertas y flujo de aprobación.
A9: Financiación de ventas comerciales | B9: 2.4 Seguimiento de performance comercial y rentabilidad de ventas | C9: Evaluar si la función financiera monitoriza la conversión, rentabilidad, margen, desviaciones y cumplimiento económico de la actividad comercial. | D9: Seguimiento centrado en ventas o ingresos, con baja visibilidad de margen, coste de servir o desviaciones frente a oferta. | E9: Reporting comercial-financiero básico, con análisis de margen parcial y seguimiento manual de ofertas relevantes. | F9: Performance comercial monitorizada con KPIs de pipeline, conversión, margen, desviación oferta-real y rentabilidad por cliente/canal/producto. | G9: Reporting integrado de ventas, margen, cash, descuentos, forecast y acciones, con owners y revisión periódica de performance. | H9: IA genera conclusiones de rendimiento comercial, identifica oportunidades de mejora, riesgos de margen, fuga de ingresos y acciones personalizadas por cliente, canal o producto. | I9: Operaciones comerciales inteligentes; Personalización de ventas y marketing; Detección de fugas de ingresos | M9: =IF(COUNT(J9:L9)=0,"",ROUND(AVERAGE(J9:L9),0)) | N9: =IF(M9="","",CHOOSE(M9,"1 - Inicial","2 - Estructurado","3 - Estandarizado","4 - Optimizado","5 - Avanzado/Referente")) | O9: =IF(M9="","",MAX(0,4-M9)) | P9: =IF(O9="","",IF(O9>=3,"Alta",IF(O9=2,"Media",IF(O9=1,"Media","Baja")))) | Q9: ¿Se mide margen real vs ofertado? ¿Se analiza performance por cliente/canal/producto? ¿Se identifican fugas de margen? ¿Se generan acciones comerciales-financieras? | R9: Dashboard comercial-financiero; pipeline; márgenes; descuentos; revenue leakage; actas de performance; acciones comerciales. | S9: Rediseñar los informes comercial-financieros con KPIs de margen, conversión, fugas, previsión, responsables y acciones de mejora.
A10: Financiación de la fabricación y la cadena de suministro | B10: 3.1 Planificación financiera de operaciones y supply chain | C10: Evaluar si la planificación financiera de fabricación, logística, inventarios y cadena de suministro está integrada con demanda, capacidad y presupuesto. | D10: Planificación financiera operativa manual, desconectada de demanda, capacidad, inventario o restricciones de supply chain. | E10: Forecast operativo-financiero básico, con inputs parciales de demanda, producción o logística y alta dependencia de Excel. | F10: Planificación estructurada con drivers de demanda, producción, logística, inventario, costes y responsables definidos. | G10: Planificación integrada con S&OP/IBP, presupuesto, forecast, capacidad, cash, riesgos y escenarios operativos. | H10: Planificación integrada de negocio basada en IA, con simulación de demanda, capacidad, costes, inventario y restricciones, y recomendación de decisiones operativas y financieras. | I10: Operaciones autónomas de cadena de suministro; Planificación integrada de negocio; Gestión dinámica de inventario | M10: =IF(COUNT(J10:L10)=0,"",ROUND(AVERAGE(J10:L10),0)) | N10: =IF(M10="","",CHOOSE(M10,"1 - Inicial","2 - Estructurado","3 - Estandarizado","4 - Optimizado","5 - Avanzado/Referente")) | O10: =IF(M10="","",MAX(0,4-M10)) | P10: =IF(O10="","",IF(O10>=3,"Alta",IF(O10=2,"Media",IF(O10=1,"Media","Baja")))) | Q10: ¿Se conecta la planificación financiera con demanda y capacidad? ¿Existe integración S&OP/IBP? ¿Se modelizan escenarios de supply chain? ¿Se conecta con presupuesto y forecast? | R10: Plan operativo-financiero; S&OP/IBP; forecast de demanda; capacidad; costes logísticos; inventarios; escenarios. | S10: Implantar planificación financiera integrada de operaciones y cadena de suministro con drivers, escenarios, capacidad, inventario y previsión.
A11: Financiación de la fabricación y la cadena de suministro | B11: 3.2 Control de costes de fabricación, logística y servicio | C11: Evaluar la capacidad para medir, controlar y explicar costes de producción, logística, mantenimiento, calidad y servicio. | D11: Costes operativos controlados de forma agregada y retrospectiva, con baja trazabilidad por driver, centro, línea o producto. | E11: Reporting básico de costes con análisis manual de desviaciones y criterios variables por planta, operación o unidad. | F11: Modelo de coste definido por driver, centro, línea, producto y actividad, con análisis recurrente de desviaciones. | G11: Control integrado de costes con productividad, calidad, mantenimiento, logística, inventarios, acciones correctivas y forecast. | H11: IA identifica patrones de coste, anomalías operativas, mantenimiento predictivo y oportunidades de eficiencia con recomendaciones cuantificadas. | I11: Mantenimiento predictivo de activos; Recomendación de demanda, coste y precio | M11: =IF(COUNT(J11:L11)=0,"",ROUND(AVERAGE(J11:L11),0)) | N11: =IF(M11="","",CHOOSE(M11,"1 - Inicial","2 - Estructurado","3 - Estandarizado","4 - Optimizado","5 - Avanzado/Referente")) | O11: =IF(M11="","",MAX(0,4-M11)) | P11: =IF(O11="","",IF(O11>=3,"Alta",IF(O11=2,"Media",IF(O11=1,"Media","Baja")))) | Q11: ¿Se conocen drivers de coste operativo? ¿Se analiza desviación por planta/línea/producto? ¿Se conectan costes con calidad y productividad? ¿Se generan acciones de eficiencia? | R11: Modelo de costes; costes estándar/reales; desviaciones; KPIs de productividad; mantenimiento; calidad; logística; planes de eficiencia. | S11: Crear modelo de control de costes operativos con drivers, desviaciones, productividad, calidad, mantenimiento y acciones de mejora.
A12: Financiación de la fabricación y la cadena de suministro | B12: 3.3 Gestión financiera de inventarios y capital circulante operativo | C12: Evaluar si Finanzas monitoriza y optimiza inventarios, obsolescencia, rotación, working capital y necesidades de liquidez operativa. | D12: Inventarios y working capital operativos gestionados con visibilidad limitada, análisis retrospectivo y baja conexión con decisiones de producción o compra. | E12: Seguimiento básico de inventario, rotación y obsolescencia, con acciones puntuales y análisis manual. | F12: KPIs de inventario y capital circulante definidos, con owners, reporting periódico y análisis por driver, material, producto o ubicación. | G12: Gestión integrada de inventario, demanda, producción, compras, servicio, cash y riesgo de obsolescencia, con acciones y seguimiento. | H12: Optimización predictiva de inventario y capital circulante con IA, anticipando demanda, obsolescencia, rupturas, exceso de stock y necesidades de caja. | I12: Gestión dinámica de inventario; Operaciones autónomas de cadena de suministro; Previsión predictiva de flujo de caja | M12: =IF(COUNT(J12:L12)=0,"",ROUND(AVERAGE(J12:L12),0)) | N12: =IF(M12="","",CHOOSE(M12,"1 - Inicial","2 - Estructurado","3 - Estandarizado","4 - Optimizado","5 - Avanzado/Referente")) | O12: =IF(M12="","",MAX(0,4-M12)) | P12: =IF(O12="","",IF(O12>=3,"Alta",IF(O12=2,"Media",IF(O12=1,"Media","Baja")))) | Q12: ¿Se mide rotación, obsolescencia y cobertura? ¿Inventario se conecta con cash y forecast? ¿Se anticipan rupturas/excesos? ¿Hay acciones sobre working capital? | R12: KPIs de inventario; DIO; obsolescencia; stock-outs; slow movers; forecast de inventario; reporting de working capital. | S12: Implantar modelo financiero de inventarios y capital circulante con KPIs, escenarios, alertas de obsolescencia y acciones de optimización.
A13: Financiación de la fabricación y la cadena de suministro | B13: 3.4 Resiliencia, riesgo y eficiencia de la cadena de suministro | C13: Evaluar si se cuantifican riesgos, disrupciones, dependencias, resiliencia y eficiencia financiera de la cadena de suministro. | D13: Riesgos de supply chain evaluados de forma cualitativa o reactiva, sin cuantificación financiera sistemática. | E13: Análisis puntuales de riesgos relevantes, con estimaciones manuales de impacto y planes de mitigación limitados. | F13: Modelo de riesgos operativos-financieros definido, con escenarios de impacto, criticidad, proveedores/materiales clave y responsables. | G13: Gestión integrada de resiliencia con coste, servicio, inventario, proveedores, logística, continuidad y planes de contingencia cuantificados. | H13: IA monitoriza señales internas/externas de riesgo, simula impactos financieros y recomienda acciones de mitigación, aprovisionamiento, inventario o red logística. | I13: Planificación logística resiliente; Operaciones autónomas de cadena de suministro | M13: =IF(COUNT(J13:L13)=0,"",ROUND(AVERAGE(J13:L13),0)) | N13: =IF(M13="","",CHOOSE(M13,"1 - Inicial","2 - Estructurado","3 - Estandarizado","4 - Optimizado","5 - Avanzado/Referente")) | O13: =IF(M13="","",MAX(0,4-M13)) | P13: =IF(O13="","",IF(O13>=3,"Alta",IF(O13=2,"Media",IF(O13=1,"Media","Baja")))) | Q13: ¿Se cuantifican riesgos de supply chain? ¿Existen escenarios de disrupción? ¿Se valoran trade-offs coste/servicio/riesgo? ¿Hay planes de contingencia financieros? | R13: Mapa de riesgos; escenarios; proveedores críticos; planes de contingencia; KPIs de servicio; costes logísticos; análisis de impacto. | S13: Desarrollar modelo financiero de resiliencia de la cadena de suministro con riesgos, escenarios, impacto económico, planes de mitigación y seguimiento.
... A17: Precios y rentabilidad | B17: 4.4 Seguimiento de margen, leakage y creación de valor | C17: Evaluar si se monitorizan desviaciones de margen, revenue leakage, cumplimiento de precio y palancas de creación de valor. | D17: Seguimiento de margen tardío y agregado, con baja capacidad para identificar causas, fugas o acciones correctivas. | E17: Análisis periódico de margen y descuentos, con identificación manual de desviaciones relevantes. | F17: Modelo de performance de margen con drivers, owners, desviaciones, leakage, acciones y seguimiento por dimensión. | G17: Margin management integrado con pricing, ventas, costes, mix, contratos, forecast y rutinas de gestión orientadas a acción. | H17: IA detecta fuga de ingresos y desviaciones tempranas, explica drivers de margen, recomienda acciones de precio/mix/coste y cuantifica impacto esperado en valor. | I17: Detección de fugas de ingresos; Analista digital de Finanzas bajo demanda; Análisis de desviaciones con explicación automática | M17: =IF(COUNT(J17:L17)=0,"",ROUND(AVERAGE(J17:L17),0)) | N17: =IF(M17="","",CHOOSE(M17,"1 - Inicial","2 - Estructurado","3 - Estandarizado","4 - Optimizado","5 - Avanzado/Referente")) | O17: =IF(M17="","",MAX(0,4-M17)) | P17: =IF(O17="","",IF(O17>=3,"Alta",IF(O17=2,"Media",IF(O17=1,"Media","Baja")))) | Q17: ¿Se monitoriza margen por driver? ¿Se detecta revenue leakage? ¿Hay owners de acciones de margen? ¿Se cuantifica impacto de acciones? | R17: Dashboard de margen; análisis de leakage; variaciones de precio/mix/coste; contratos; acciones; seguimiento de beneficios. | S17: Crear modelo de gestión del rendimiento del margen con drivers, fugas, responsables, acciones, previsión e impacto económico cuantificado.

Sheet Resumen
A1: Capacidad | B1: Score Procesos | C1: Score Tecnología | D1: Score Organización | E1: Score Medio | F1: Gap vs objetivo | G1: Prioridad
A2: Financiación I+D | B2: =IFERROR(ROUND(AVERAGEIF(Assessment!$A:$A,A2,Assessment!$J:$J),0),"") | C2: =IFERROR(ROUND(AVERAGEIF(Assessment!$A:$A,A2,Assessment!$K:$K),0),"") | D2: =IFERROR(ROUND(AVERAGEIF(Assessment!$A:$A,A2,Assessment!$L:$L),0),"") | E2: =IFERROR(ROUND(AVERAGE(B2:D2),0),"") | F2: =IF(E2="","",MAX(0,4-E2)) | G2: =IF(F2="","",IF(F2>=3,"Alta",IF(F2=2,"Media",IF(F2=1,"Media","Baja"))))
A3: Financiación de ventas comerciales | B3: =IFERROR(ROUND(AVERAGEIF(Assessment!$A:$A,A3,Assessment!$J:$J),0),"") | C3: =IFERROR(ROUND(AVERAGEIF(Assessment!$A:$A,A3,Assessment!$K:$K),0),"") | D3: =IFERROR(ROUND(AVERAGEIF(Assessment!$A:$A,A3,Assessment!$L:$L),0),"") | E3: =IFERROR(ROUND(AVERAGE(B3:D3),0),"") | F3: =IF(E3="","",MAX(0,4-E3)) | G3: =IF(F3="","",IF(F3>=3,"Alta",IF(F3=2,"Media",IF(F3=1,"Media","Baja"))))
A4: Financiación de la fabricación y la cadena de suministro | B4: =IFERROR(ROUND(AVERAGEIF(Assessment!$A:$A,A4,Assessment!$J:$J),0),"") | C4: =IFERROR(ROUND(AVERAGEIF(Assessment!$A:$A,A4,Assessment!$K:$K),0),"") | D4: =IFERROR(ROUND(AVERAGEIF(Assessment!$A:$A,A4,Assessment!$L:$L),0),"") | E4: =IFERROR(ROUND(AVERAGE(B4:D4),0),"") | F4: =IF(E4="","",MAX(0,4-E4)) | G4: =IF(F4="","",IF(F4>=3,"Alta",IF(F4=2,"Media",IF(F4=1,"Media","Baja"))))
A5: Precios y rentabilidad | B5: =IFERROR(ROUND(AVERAGEIF(Assessment!$A:$A,A5,Assessment!$J:$J),0),"") | C5: =IFERROR(ROUND(AVERAGEIF(Assessment!$A:$A,A5,Assessment!$K:$K),0),"") | D5: =IFERROR(ROUND(AVERAGEIF(Assessment!$A:$A,A5,Assessment!$L:$L),0),"") | E5: =IFERROR(ROUND(AVERAGE(B5:D5),0),"") | F5: =IF(E5="","",MAX(0,4-E5)) | G5: =IF(F5="","",IF(F5>=3,"Alta",IF(F5=2,"Media",IF(F5=1,"Media","Baja"))))
A6: Score global dominio | B6: =IFERROR(ROUND(AVERAGE(B2:B5),0),"") | C6: =IFERROR(ROUND(AVERAGE(C2:C5),0),"") | D6: =IFERROR(ROUND(AVERAGE(D2:D5),0),"") | E6: =IFERROR(ROUND(AVERAGE(E2:E5),0),"") | F6: =IF(E6="","",MAX(0,4-E6)) | G6: =IF(F6="","",IF(F6>=3,"Alta",IF(F6=2,"Media",IF(F6=1,"Media","Baja"))))

Sheet Heatmap
A1: Capacidad | B1: Subcapacidad | C1: Procesos | D1: Tecnología | E1: Organización | F1: Score medio | G1: Gap | H1: Prioridad
A2: Financiación I+D | B2: 1.1 Gobierno y portfolio de iniciativas de I+D | C2: =Assessment!J2 -> 0 | D2: =Assessment!K2 -> 0 | E2: =Assessment!L2 -> 0 | F2: =Assessment!M2 | G2: =Assessment!O2 | H2: =Assessment!P2
A3: Financiación I+D | B3: 1.2 Planificación y control económico de proyectos de I+D | C3: =Assessment!J3 -> 0 | D3: =Assessment!K3 -> 0 | E3: =Assessment!L3 -> 0 | F3: =Assessment!M3 | G3: =Assessment!O3 | H3: =Assessment!P3
A4: Financiación I+D | B4: 1.3 Financiación, subvenciones e incentivos de I+D | C4: =Assessment!J4 -> 0 | D4: =Assessment!K4 -> 0 | E4: =Assessment!L4 -> 0 | F4: =Assessment!M4 | G4: =Assessment!O4 | H4: =Assessment!P4
A5: Financiación I+D | B5: 1.4 Medición de valor y retorno de la innovación | C5: =Assessment!J5 -> 0 | D5: =Assessment!K5 -> 0 | E5: =Assessment!L5 -> 0 | F5: =Assessment!M5 | G5: =Assessment!O5 | H5: =Assessment!P5
A6: Financiación de ventas comerciales | B6: 2.1 Gobierno financiero de propuestas y condiciones comerciales | C6: =Assessment!J6 -> 0 | D6: =Assessment!K6 -> 0 | E6: =Assessment!L6 -> 0 | F6: =Assessment!M6 | G6: =Assessment!O6 | H6: =Assessment!P6
A7: Financiación de ventas comerciales | B7: 2.2 Evaluación financiera de oportunidades, RFPs y ofertas | C7: =Assessment!J7 -> 0 | D7: =Assessment!K7 -> 0 | E7: =Assessment!L7 -> 0 | F7: =Assessment!M7 | G7: =Assessment!O7 | H7: =Assessment!P7
A8: Financiación de ventas comerciales | B8: 2.3 Gestión de riesgos comerciales y exposición financiera | C8: =Assessment!J8 -> 0 | D8: =Assessment!K8 -> 0 | E8: =Assessment!L8 -> 0 | F8: =Assessment!M8 | G8: =Assessment!O8 | H8: =Assessment!P8
A9: Financiación de ventas comerciales | B9: 2.4 Seguimiento de performance comercial y rentabilidad de ventas | C9: =Assessment!J9 -> 0 | D9: =Assessment!K9 -> 0 | E9: =Assessment!L9 -> 0 | F9: =Assessment!M9 | G9: =Assessment!O9 | H9: =Assessment!P9
A10: Financiación de la fabricación y la cadena de suministro | B10: 3.1 Planificación financiera de operaciones y supply chain | C10: =Assessment!J10 -> 0 | D10: =Assessment!K10 -> 0 | E10: =Assessment!L10 -> 0 | F10: =Assessment!M10 | G10: =Assessment!O10 | H10: =Assessment!P10
A11: Financiación de la fabricación y la cadena de suministro | B11: 3.2 Control de costes de fabricación, logística y servicio | C11: =Assessment!J11 -> 0 | D11: =Assessment!K11 -> 0 | E11: =Assessment!L11 -> 0 | F11: =Assessment!M11 | G11: =Assessment!O11 | H11: =Assessment!P11
A12: Financiación de la fabricación y la cadena de suministro | B12: 3.3 Gestión financiera de inventarios y capital circulante operativo | C12: =Assessment!J12 -> 0 | D12: =Assessment!K12 -> 0 | E12: =Assessment!L12 -> 0 | F12: =Assessment!M12 | G12: =Assessment!O12 | H12: =Assessment!P12
A13: Financiación de la fabricación y la cadena de suministro | B13: 3.4 Resiliencia, riesgo y eficiencia de la cadena de suministro | C13: =Assessment!J13 -> 0 | D13: =Assessment!K13 -> 0 | E13: =Assessment!L13 -> 0 | F13: =Assessment!M13 | G13: =Assessment!O13 | H13: =Assessment!P13
... A17: Precios y rentabilidad | B17: 4.4 Seguimiento de margen, leakage y creación de valor | C17: =Assessment!J17 -> 0 | D17: =Assessment!K17 -> 0 | E17: =Assessment!L17 -> 0 | F17: =Assessment!M17 | G17: =Assessment!O17 | H17: =Assessment!P17

Sheet Roadmap
A1: Capacidad | B1: Subcapacidad | C1: Gap | D1: Prioridad | E1: Iniciativa sugerida | F1: Casos AI asociados | G1: Oleada | H1: Owner | I1: Estado | J1: Comentarios
A2: Financiación I+D | B2: 1.1 Gobierno y portfolio de iniciativas de I+D | C2: =Assessment!O2 | D2: =Assessment!P2 | E2: Diseñar modelo de gobierno de la cartera de I+D con criterios de valor, riesgo, alineamiento estratégico, financiación y seguimiento periódico. | F2: Diseño de producto orquestado por IA; Ensayos clínicos más inteligentes; Descubrimiento autónomo de fármacos | G2: =IF(C2="","",IF(C2>=3,"Oleada 1",IF(C2=2,"Oleada 2",IF(C2=1,"Oleada 3","")))) | I2: No iniciado
A3: Financiación I+D | B3: 1.2 Planificación y control económico de proyectos de I+D | C3: =Assessment!O3 | D3: =Assessment!P3 | E3: Implantar modelo de control económico de proyectos de I+D con presupuesto, previsión, hitos, desviaciones, riesgos y acciones correctivas. | F3: Diseño de producto orquestado por IA; Ensayos clínicos más inteligentes; Descubrimiento autónomo de fármacos | G3: =IF(C3="","",IF(C3>=3,"Oleada 1",IF(C3=2,"Oleada 2",IF(C3=1,"Oleada 3","")))) | I3: No iniciado
A4: Financiación I+D | B4: 1.3 Financiación, subvenciones e incentivos de I+D | C4: =Assessment!O4 | D4: =Assessment!P4 | E4: Crear proceso estructurado de financiación e incentivos de I+D con análisis de elegibilidad, evidencias, flujo de aprobación y seguimiento financiero. | F4: Cumplimiento regulatorio automatizado; Interpretación de normativa financiera; Diseño de producto orquestado por IA; Determinación de elegibilidad para incentivos | G4: =IF(C4="","",IF(C4>=3,"Oleada 1",IF(C4=2,"Oleada 2",IF(C4=1,"Oleada 3","")))) | I4: No iniciado
A5: Financiación I+D | B5: 1.4 Medición de valor y retorno de la innovación | C5: =Assessment!O5 | D5: =Assessment!P5 | E5: Definir modelo de medición de valor de I+D con KPIs, beneficios esperados y reales, responsables, revisión de la cartera y aprendizaje recurrente. | F5: Descubrimiento autónomo de fármacos; Diseño de producto orquestado por IA; Recomendaciones de acción a nivel de proyecto | G5: =IF(C5="","",IF(C5>=3,"Oleada 1",IF(C5=2,"Oleada 2",IF(C5=1,"Oleada 3","")))) | I5: No iniciado
A6: Financiación de ventas comerciales | B6: 2.1 Gobierno financiero de propuestas y condiciones comerciales | C6: =Assessment!O6 | D6: =Assessment!P6 | E6: Diseñar gobierno financiero de propuestas comerciales con reglas de margen, descuentos, riesgos, aprobaciones y trazabilidad de principio a fin. | F6: Asistente de RFP y de conocimiento comercial; Operaciones comerciales inteligentes | G6: =IF(C6="","",IF(C6>=3,"Oleada 1",IF(C6=2,"Oleada 2",IF(C6=1,"Oleada 3","")))) | I6: No iniciado
A7: Financiación de ventas comerciales | B7: 2.2 Evaluación financiera de oportunidades, RFPs y ofertas | C7: =Assessment!O7 | D7: =Assessment!P7 | E7: Implantar modelo de evaluación financiera de oportunidades y RFPs con análisis económico, riesgos, capacidad, probabilidad y priorización de la cartera comercial. | F7: Asistente de RFP y de conocimiento comercial; Operaciones comerciales inteligentes; Personalización de ventas y marketing | G7: =IF(C7="","",IF(C7>=3,"Oleada 1",IF(C7=2,"Oleada 2",IF(C7=1,"Oleada 3","")))) | I7: No iniciado
A8: Financiación de ventas comerciales | B8: 2.3 Gestión de riesgos comerciales y exposición financiera | C8: =Assessment!O8 | D8: =Assessment!P8 | E8: Construir modelo de riesgo comercial financiero con puntuación de riesgo, límites, condiciones, exposición, alertas y flujo de aprobación. | F8: Agentes de IA para análisis de riesgo crediticio; Condiciones de pago óptimas para el DSO; Operaciones comerciales inteligentes | G8: =IF(C8="","",IF(C8>=3,"Oleada 1",IF(C8=2,"Oleada 2",IF(C8=1,"Oleada 3","")))) | I8: No iniciado
A9: Financiación de ventas comerciales | B9: 2.4 Seguimiento de performance comercial y rentabilidad de ventas | C9: =Assessment!O9 | D9: =Assessment!P9 | E9: Rediseñar los informes comercial-financieros con KPIs de margen, conversión, fugas, previsión, responsables y acciones de mejora. | F9: Operaciones comerciales inteligentes; Personalización de ventas y marketing; Detección de fugas de ingresos | G9: =IF(C9="","",IF(C9>=3,"Oleada 1",IF(C9=2,"Oleada 2",IF(C9=1,"Oleada 3","")))) | I9: No iniciado
A10: Financiación de la fabricación y la cadena de suministro | B10: 3.1 Planificación financiera de operaciones y supply chain | C10: =Assessment!O10 | D10: =Assessment!P10 | E10: Implantar planificación financiera integrada de operaciones y cadena de suministro con drivers, escenarios, capacidad, inventario y previsión. | F10: Operaciones autónomas de cadena de suministro; Planificación integrada de negocio; Gestión dinámica de inventario | G10: =IF(C10="","",IF(C10>=3,"Oleada 1",IF(C10=2,"Oleada 2",IF(C10=1,"Oleada 3","")))) | I10: No iniciado
A11: Financiación de la fabricación y la cadena de suministro | B11: 3.2 Control de costes de fabricación, logística y servicio | C11: =Assessment!O11 | D11: =Assessment!P11 | E11: Crear modelo de control de costes operativos con drivers, desviaciones, productividad, calidad, mantenimiento y acciones de mejora. | F11: Mantenimiento predictivo de activos; Recomendación de demanda, coste y precio | G11: =IF(C11="","",IF(C11>=3,"Oleada 1",IF(C11=2,"Oleada 2",IF(C11=1,"Oleada 3","")))) | I11: No iniciado
A12: Financiación de la fabricación y la cadena de suministro | B12: 3.3 Gestión financiera de inventarios y capital circulante operativo | C12: =Assessment!O12 | D12: =Assessment!P12 | E12: Implantar modelo financiero de inventarios y capital circulante con KPIs, escenarios, alertas de obsolescencia y acciones de optimización. | F12: Gestión dinámica de inventario; Operaciones autónomas de cadena de suministro; Previsión predictiva de flujo de caja | G12: =IF(C12="","",IF(C12>=3,"Oleada 1",IF(C12=2,"Oleada 2",IF(C12=1,"Oleada 3","")))) | I12: No iniciado
A13: Financiación de la fabricación y la cadena de suministro | B13: 3.4 Resiliencia, riesgo y eficiencia de la cadena de suministro | C13: =Assessment!O13 | D13: =Assessment!P13 | E13: Desarrollar modelo financiero de resiliencia de la cadena de suministro con riesgos, escenarios, impacto económico, planes de mitigación y seguimiento. | F13: Planificación logística resiliente; Operaciones autónomas de cadena de suministro | G13: =IF(C13="","",IF(C13>=3,"Oleada 1",IF(C13=2,"Oleada 2",IF(C13=1,"Oleada 3","")))) | I13: No iniciado
... A17: Precios y rentabilidad | B17: 4.4 Seguimiento de margen, leakage y creación de valor | C17: =Assessment!O17 | D17: =Assessment!P17 | E17: Crear modelo de gestión del rendimiento del margen con drivers, fugas, responsables, acciones, previsión e impacto económico cuantificado. | F17: Detección de fugas de ingresos; Analista digital de Finanzas bajo demanda; Análisis de desviaciones con explicación automática | G17: =IF(C17="","",IF(C17>=3,"Oleada 1",IF(C17=2,"Oleada 2",IF(C17=1,"Oleada 3","")))) | I17: No iniciado

Sheet AI Overlay
A1: Capacidad | B1: Subcapacidad | C1: Casos de uso AI asociados | D1: Aplicación en nivel avanzado | E1: Fuente
A2: Financiación I+D | B2: 1.1 Gobierno y portfolio de iniciativas de I+D | C2: Diseño de producto orquestado por IA; Ensayos clínicos más inteligentes; Descubrimiento autónomo de fármacos | D2: Cartera de innovación dinámica y basada en IA, con priorización por escenarios, señales de mercado, probabilidad de éxito y ROI esperado, y recomendación de asignación de capital. | E2: F3M_AI_Mapping_Consolidado_v1.xlsx
A3: Financiación I+D | B3: 1.2 Planificación y control económico de proyectos de I+D | C3: Diseño de producto orquestado por IA; Ensayos clínicos más inteligentes; Descubrimiento autónomo de fármacos | D3: Planificación predictiva de costes y avance de I+D, con simulación de escenarios, detección temprana de desviaciones y recomendaciones sobre continuidad, aceleración o cancelación. | E3: F3M_AI_Mapping_Consolidado_v1.xlsx
A4: Financiación I+D | B4: 1.3 Financiación, subvenciones e incentivos de I+D | C4: Cumplimiento regulatorio automatizado; Interpretación de normativa financiera; Diseño de producto orquestado por IA; Determinación de elegibilidad para incentivos | D4: Motor inteligente de identificación y optimización de incentivos, con cribado normativo, elegibilidad predictiva, generación asistida de documentación y alertas de cumplimiento. | E4: F3M_AI_Mapping_Consolidado_v1.xlsx
A5: Financiación I+D | B5: 1.4 Medición de valor y retorno de la innovación | C5: Descubrimiento autónomo de fármacos; Diseño de producto orquestado por IA; Recomendaciones de acción a nivel de proyecto | D5: Medición avanzada de valor con modelos predictivos, análisis de contribución, escenarios de monetización y recomendaciones de inversión/desinversión en innovación. | E5: F3M_AI_Mapping_Consolidado_v1.xlsx
A6: Financiación de ventas comerciales | B6: 2.1 Gobierno financiero de propuestas y condiciones comerciales | C6: Asistente de RFP y de conocimiento comercial; Operaciones comerciales inteligentes | D6: Asistente IA para propuestas comerciales que recomienda condiciones, identifica riesgos, estima rentabilidad y guía aprobaciones según margen, cliente y probabilidad de conversión. | E6: F3M_AI_Mapping_Consolidado_v1.xlsx
A7: Financiación de ventas comerciales | B7: 2.2 Evaluación financiera de oportunidades, RFPs y ofertas | C7: Asistente de RFP y de conocimiento comercial; Operaciones comerciales inteligentes; Personalización de ventas y marketing | D7: Asistente de IA para RFP que resume los requisitos, estima la rentabilidad esperada, identifica riesgos, propone respuestas y prioriza oportunidades por valor ajustado a probabilidad y riesgo. | E7: F3M_AI_Mapping_Consolidado_v1.xlsx
A8: Financiación de ventas comerciales | B8: 2.3 Gestión de riesgos comerciales y exposición financiera | C8: Agentes de IA para análisis de riesgo crediticio; Condiciones de pago óptimas para el DSO; Operaciones comerciales inteligentes | D8: Puntuación predictiva del riesgo comercial y de la exposición, con recomendación de condiciones, garantías, límites, precio y acciones preventivas por cliente u oportunidad. | E8: F3M_AI_Mapping_Consolidado_v1.xlsx
A9: Financiación de ventas comerciales | B9: 2.4 Seguimiento de performance comercial y rentabilidad de ventas | C9: Operaciones comerciales inteligentes; Personalización de ventas y marketing; Detección de fugas de ingresos | D9: IA genera conclusiones de rendimiento comercial, identifica oportunidades de mejora, riesgos de margen, fuga de ingresos y acciones personalizadas por cliente, canal o producto. | E9: F3M_AI_Mapping_Consolidado_v1.xlsx
A10: Financiación de la fabricación y la cadena de suministro | B10: 3.1 Planificación financiera de operaciones y supply chain | C10: Operaciones autónomas de cadena de suministro; Planificación integrada de negocio; Gestión dinámica de inventario | D10: Planificación integrada de negocio basada en IA, con simulación de demanda, capacidad, costes, inventario y restricciones, y recomendación de decisiones operativas y financieras. | E10: F3M_AI_Mapping_Consolidado_v1.xlsx
A11: Financiación de la fabricación y la cadena de suministro | B11: 3.2 Control de costes de fabricación, logística y servicio | C11: Mantenimiento predictivo de activos; Recomendación de demanda, coste y precio | D11: IA identifica patrones de coste, anomalías operativas, mantenimiento predictivo y oportunidades de eficiencia con recomendaciones cuantificadas. | E11: F3M_AI_Mapping_Consolidado_v1.xlsx
A12: Financiación de la fabricación y la cadena de suministro | B12: 3.3 Gestión financiera de inventarios y capital circulante operativo | C12: Gestión dinámica de inventario; Operaciones autónomas de cadena de suministro; Previsión predictiva de flujo de caja | D12: Optimización predictiva de inventario y capital circulante con IA, anticipando demanda, obsolescencia, rupturas, exceso de stock y necesidades de caja. | E12: F3M_AI_Mapping_Consolidado_v1.xlsx
... A17: Precios y rentabilidad | B17: 4.4 Seguimiento de margen, leakage y creación de valor | C17: Detección de fugas de ingresos; Analista digital de Finanzas bajo demanda; Análisis de desviaciones con explicación automática | D17: IA detecta fuga de ingresos y desviaciones tempranas, explica drivers de margen, recomienda acciones de precio/mix/coste y cuantifica impacto esperado en valor. | E17: F3M_AI_Mapping_Consolidado_v1.xlsx

Sheet Guias scoring
A1: GUÍAS DE SCORING F3M
A2: PROCESOS
A3: Nivel 1 - Inicial | B3: Proceso inexistente, manual o ad hoc.
A4: Nivel 2 - Estructurado | B4: Proceso parcial, definido con variabilidad y dependencias manuales.
A5: Nivel 3 - Estandarizado | B5: Proceso documentado, homogéneo y repetible.
A6: Nivel 4 - Optimizado | B6: Proceso medido, eficiente, con controles y mejora continua.
A7: Nivel 5 - Avanzado | B7: Proceso integrado end-to-end, orientado a decisión y habilitado por automatización/AI cuando aplique.
A9: TECNOLOGÍA
A10: Nivel 1 - Inicial | B10: Excel/manual, sin integración.
A11: Nivel 2 - Estructurado | B11: Herramientas parciales o locales, con baja integración.
A12: Nivel 3 - Estandarizado | B12: Herramienta corporativa y reglas definidas.
A13: Nivel 4 - Optimizado | B13: Integración end-to-end, automatización y controles tecnológicos.
A14: Nivel 5 - Avanzado | B14: Analítica avanzada, AI/GenAI, detección predictiva, autoservicio o workflow inteligente.
A16: ORGANIZACIÓN
A17: Nivel 1 - Inicial | B17: Roles poco claros y alta dependencia de personas.
A18: Nivel 2 - Estructurado | B18: Roles parcialmente definidos y coordinación manual.
A19: Nivel 3 - Estandarizado | B19: Roles, ownership y accountability claros.
A20: Nivel 4 - Optimizado | B20: Organización alineada con procesos, KPIs y mejora continua.
A21: Nivel 5 - Avanzado | B21: Equipos orientados a business partnering, eficiencia, colaboración y generación de valor.
A23: REGLAS DE ORO
A24: 1 | B24: Puntuar el estado actual, no el objetivo.
A25: 2 | B25: No mezclar palancas: procesos, tecnología y organización se puntúan por separado.
A26: 3 | B26: Sustentar cada score con evidencias.
A27: 4 | B27: No sobrevalorar la tecnología si el proceso o la adopción no están maduros.

Sheet Instrucciones (2)
A1: F3M - FP&A | Assessment-ready
A2: Uso del fichero
A3: 1. En 'Assessment', puntuar cada subcapacidad en las tres palancas: Procesos, Tecnología y Organización.
A4: 2. Utilizar valores enteros de 1 a 5, donde 1 = Inicial y 5 = Avanzado/Referente.
A5: 3. El Score Medio, Nivel resultante, Gap y Prioridad se calculan automáticamente.
A6: 4. Objetivo de madurez utilizado para el gap: Nivel 4 - Optimizado.
A7: 5. 'Resumen' consolida resultados por capacidad y gráfico ejecutivo.
A8: 6. 'Heatmap' facilita la lectura visual por subcapacidad y palanca.
A9: 7. 'Roadmap' convierte gaps en iniciativas sugeridas y oleadas.
A10: Escala F3M
A11: 1 - Inicial: modelo básico, operativo, heterogéneo y poco formalizado.
A12: 2 - Estructurado: prácticas definidas, con consistencia parcial y dependencias manuales.
... A15: 5 - Avanzado/Referente: modelo maduro, estratégico, anticipativo y orientado a generación de valor.
