Workbook

Sheet Assessment
A1: Capacidad | B1: Subcapacidad | C1: Objetivo de evaluación | D1: Nivel 1 - Inicial | E1: Nivel 2 - Estructurado | F1: Nivel 3 - Estandarizado | G1: Nivel 4 - Optimizado | H1: Nivel 5 - Avanzado/Referente | I1: Score Procesos | J1: Score Tecnología | K1: Score Organización | L1: Score Medio | M1: Nivel resultante | N1: Gap vs objetivo | O1: Prioridad | P1: Preguntas clave | Q1: Evidencias | R1: Iniciativa sugerida | S1: Comentarios / hallazgos
A2: Presupuestos y previsiones | B2: 1.1 Gobierno del proceso presupuestario y forecast | C2: Evaluar si existe un proceso formal, gobernado y calendarizado para presupuesto, forecast y revisiones periódicas. | D2: Proceso ad hoc, con calendario poco formalizado, criterios heterogéneos y dependencia elevada de personas clave. | E2: Existe calendario básico y responsables definidos, aunque con variabilidad entre áreas y elevada carga manual. | F2: Proceso documentado, con calendario corporativo, roles, entregables, versiones y criterios comunes. | G2: Proceso integrado con negocio, operaciones y reporting, con ciclos eficientes, control de versiones y mejora continua. | H2: Modelo rolling, ágil y orientado a escenarios, con gobierno colaborativo, alertas tempranas y capacidad de replanificación dinámica. | L2: =IF(COUNTA(I2:K2)=0,"",ROUND(AVERAGE(I2:K2),2)) -> 3 | M2: =IF(L2="","",IF(L2<1.5,"1 - Inicial",IF(L2<2.5,"2 - Estructurado",IF(L2<3.5,"3 - Estandarizado",IF(L2<4.5,"4 - Optimizado","5 - Avanzado/Referente"))))) -> 3 - Estandarizado | N2: =IF(L2="","",MAX(0,4-L2)) -> 1 | O2: =IF(L2="","",IF(N2>=2,"Alta",IF(N2>=1,"Media","Baja"))) -> Media | P2: ¿Existe calendario formal de presupuesto y forecast? ¿Están definidos roles, responsables y entregables? ¿Se controlan versiones y aprobaciones? ¿El proceso permite reforecast ágil ante cambios? | Q2: Calendario presupuestario; RACI; workflow de aprobación; plantillas; actas de comités; control de versiones. | R2: Diseñar modelo de gobierno FP&A con calendario integrado, RACI, flujo de aprobación, criterios comunes y control de versiones.
A3: Presupuestos y previsiones | B3: 1.2 Modelo presupuestario y drivers de planificación | C3: Evaluar si el presupuesto y forecast se construyen con drivers de negocio y financieros homogéneos, trazables y orientados a valor. | D3: Presupuesto incremental o histórico, con limitada conexión a drivers operativos o estratégicos. | E3: Se incorporan algunos drivers, pero de forma parcial, manual o no homogénea entre unidades. | F3: Modelo presupuestario con drivers definidos, documentados y aplicados de forma consistente. | G3: Modelo driver-based integrado con datos operativos, financieros y comerciales, con análisis de sensibilidad. | H3: Planificación predictiva y dinámica, con drivers algorítmicos, escenarios automatizados y recomendaciones para la toma de decisiones. | L3: =IF(COUNTA(I3:K3)=0,"",ROUND(AVERAGE(I3:K3),2)) | M3: =IF(L3="","",IF(L3<1.5,"1 - Inicial",IF(L3<2.5,"2 - Estructurado",IF(L3<3.5,"3 - Estandarizado",IF(L3<4.5,"4 - Optimizado","5 - Avanzado/Referente"))))) | N3: =IF(L3="","",MAX(0,4-L3)) | O3: =IF(L3="","",IF(N3>=2,"Alta",IF(N3>=1,"Media","Baja"))) | P3: ¿El presupuesto está basado en drivers? ¿Los drivers están documentados y validados? ¿Se conectan datos financieros y operativos? ¿Se realizan sensibilidades y escenarios? | Q3: Catálogo de drivers; modelo de planificación; documentación de supuestos; análisis de sensibilidad; inputs operativos. | R3: Evolucionar hacia una planificación basada en drivers, con catálogo de drivers, reglas de cálculo, trazabilidad y análisis de sensibilidad.
A4: Presupuestos y previsiones | B4: 1.3 Integración de escenarios y rolling forecast | C4: Evaluar si la organización puede generar escenarios y forecasts actualizados de forma recurrente y útil para decidir. | D4: Forecast puntual, manual y principalmente financiero, con baja conexión a cambios del negocio. | E4: Forecast recurrente, pero con escenarios limitados y dependencia de Excel o modelos no integrados. | F4: Forecast periódico con metodología común, supuestos documentados y escenarios básicos. | G4: Rolling forecast integrado con escenarios de negocio, automatización parcial y revisión de desviaciones. | H4: Forecast continuo, predictivo y orientado a decisiones, con escenarios automatizados y alertas tempranas. | L4: =IF(COUNTA(I4:K4)=0,"",ROUND(AVERAGE(I4:K4),2)) | M4: =IF(L4="","",IF(L4<1.5,"1 - Inicial",IF(L4<2.5,"2 - Estructurado",IF(L4<3.5,"3 - Estandarizado",IF(L4<4.5,"4 - Optimizado","5 - Avanzado/Referente"))))) | N4: =IF(L4="","",MAX(0,4-L4)) | O4: =IF(L4="","",IF(N4>=2,"Alta",IF(N4>=1,"Media","Baja"))) | P4: ¿Existe rolling forecast? ¿Con qué frecuencia se actualiza? ¿Se documentan supuestos? ¿Se modelizan escenarios alternativos? ¿Se usan alertas tempranas? | Q4: Modelos de forecast; supuestos; escenarios; calendario de reforecast; reporting de desviaciones; alertas. | R4: Implantar previsión continua (rolling forecast) con escenarios base, optimista y pesimista, supuestos documentados y automatización de los datos de entrada críticos.
A5: Presupuestos y previsiones | B5: 1.4 Colaboración y accountability presupuestaria | C5: Evaluar si el proceso presupuestario involucra adecuadamente a negocio, finanzas y owners, con accountability clara. | D5: Participación limitada del negocio; Finanzas consolida información sin ownership claro de hipótesis o resultados. | E5: Participación de áreas de negocio, pero con responsabilidades parciales o poco formalizadas. | F5: Roles definidos por unidad, owner de hipótesis y proceso de validación formalizado. | G5: Colaboración integrada, con workflows, trazabilidad de cambios, challenge financiero y seguimiento de compromisos. | H5: Accountability completa sobre planes y resultados, con incentivos alineados, colaboración digital y toma de decisiones basada en escenarios. | L5: =IF(COUNTA(I5:K5)=0,"",ROUND(AVERAGE(I5:K5),2)) | M5: =IF(L5="","",IF(L5<1.5,"1 - Inicial",IF(L5<2.5,"2 - Estructurado",IF(L5<3.5,"3 - Estandarizado",IF(L5<4.5,"4 - Optimizado","5 - Avanzado/Referente"))))) | N5: =IF(L5="","",MAX(0,4-L5)) | O5: =IF(L5="","",IF(N5>=2,"Alta",IF(N5>=1,"Media","Baja"))) | P5: ¿Quién es owner de cada hipótesis? ¿Existe challenge financiero al negocio? ¿Se trazan cambios y aprobaciones? ¿La accountability se mantiene tras la aprobación? | Q5: RACI; workflows; aprobaciones; trazabilidad de cambios; actas de challenge; seguimiento de compromisos. | R5: Definir la responsabilidad presupuestaria por dimensión y unidad, con flujo colaborativo, contraste financiero y seguimiento de compromisos.
A6: Informes de gestión del rendimiento | B6: 2.1 Modelo de reporting de performance | C6: Evaluar si existe un modelo de reporting de gestión alineado con objetivos, KPIs y necesidades de dirección. | D6: Reporting fragmentado, manual y orientado principalmente a información histórica. | E6: Reporting recurrente con algunos KPIs definidos, pero con formatos y criterios variables. | F6: Modelo de reporting homogéneo, con KPIs, dimensiones, periodicidad y responsables definidos. | G6: Reporting integrado con análisis de desviaciones, causas, responsables y acciones de mejora. | H6: Performance management dinámico, con KPIs predictivos, alertas y recomendaciones accionables para dirección. | L6: =IF(COUNTA(I6:K6)=0,"",ROUND(AVERAGE(I6:K6),2)) | M6: =IF(L6="","",IF(L6<1.5,"1 - Inicial",IF(L6<2.5,"2 - Estructurado",IF(L6<3.5,"3 - Estandarizado",IF(L6<4.5,"4 - Optimizado","5 - Avanzado/Referente"))))) | N6: =IF(L6="","",MAX(0,4-L6)) | O6: =IF(L6="","",IF(N6>=2,"Alta",IF(N6>=1,"Media","Baja"))) | P6: ¿Existe catálogo de KPIs? ¿El reporting está alineado con objetivos? ¿Incluye análisis causa-raíz? ¿Genera acciones y seguimiento? | Q6: Catálogo de KPIs; paquetes de reporting; dashboards; actas de revisión; planes de acción. | R6: Rediseñar los informes de gestión alrededor de objetivos, KPIs, desviaciones, causas, responsables y acciones.
A7: Informes de gestión del rendimiento | B7: 2.2 Análisis de desviaciones y causa-raíz | C7: Evaluar la capacidad de explicar desviaciones entre real, presupuesto, forecast y objetivos, identificando causas accionables. | D7: Análisis descriptivo y manual, limitado a variaciones agregadas sin explicación estructurada. | E7: Se explican desviaciones relevantes, pero con criterios no homogéneos y dependencia de análisis ad hoc. | F7: Metodología común de análisis de desviaciones por dimensión, responsable y causa. | G7: Análisis integrado con drivers, acciones correctivas, seguimiento y conexión con forecast. | H7: Análisis predictivo de desviaciones, con alertas tempranas, simulación de impactos y recomendaciones. | L7: =IF(COUNTA(I7:K7)=0,"",ROUND(AVERAGE(I7:K7),2)) | M7: =IF(L7="","",IF(L7<1.5,"1 - Inicial",IF(L7<2.5,"2 - Estructurado",IF(L7<3.5,"3 - Estandarizado",IF(L7<4.5,"4 - Optimizado","5 - Avanzado/Referente"))))) | N7: =IF(L7="","",MAX(0,4-L7)) | O7: =IF(L7="","",IF(N7>=2,"Alta",IF(N7>=1,"Media","Baja"))) | P7: ¿Se comparan real, presupuesto y forecast? ¿Se explican desviaciones por driver? ¿Hay owners y acciones? ¿El análisis actualiza previsiones? | Q7: Reportes de desviaciones; árboles de drivers; actas con acciones; forecast actualizado; dashboards. | R7: Crear metodología de análisis de desviaciones por driver, dimensión, responsable, causa-raíz, acción y seguimiento.
A8: Informes de gestión del rendimiento | B8: 2.3 Cuadros de mando y visualización ejecutiva | C8: Evaluar si la organización dispone de dashboards útiles, integrados y accionables para distintos niveles de gestión. | D8: Informes estáticos, dispersos y con alta manipulación manual. | E8: Dashboards parciales o locales, con cierta automatización pero baja integración. | F8: Cuadros de mando definidos por audiencia, con KPIs y dimensiones comunes. | G8: Dashboards integrados, autoservicio controlado, drill-down y conexión con acciones de gestión. | H8: Visualización ejecutiva avanzada, con conclusiones automáticas, alertas, narrativa analítica y soporte predictivo. | L8: =IF(COUNTA(I8:K8)=0,"",ROUND(AVERAGE(I8:K8),2)) | M8: =IF(L8="","",IF(L8<1.5,"1 - Inicial",IF(L8<2.5,"2 - Estructurado",IF(L8<3.5,"3 - Estandarizado",IF(L8<4.5,"4 - Optimizado","5 - Avanzado/Referente"))))) | N8: =IF(L8="","",MAX(0,4-L8)) | O8: =IF(L8="","",IF(N8>=2,"Alta",IF(N8>=1,"Media","Baja"))) | P8: ¿Existen dashboards por nivel directivo? ¿Permiten drill-down? ¿Hay single source of truth? ¿Se automatiza la generación? | Q8: Dashboards; modelo semántico; guía de KPIs; evidencias de automatización; accesos por perfil. | R8: Implantar cuadro de mando FP&A con KPIs homologados, navegación al detalle, acceso por perfil y automatización de datos.
A9: Informes de gestión del rendimiento | B9: 2.4 Rutinas de performance y toma de acciones | C9: Evaluar si el reporting se integra en rutinas de gestión que generan decisiones, acciones y seguimiento de impactos. | D9: El reporting se distribuye pero no existe rutina formal de revisión ni seguimiento de acciones. | E9: Existen reuniones de revisión, pero con baja trazabilidad de decisiones y acciones. | F9: Rutinas periódicas de performance con agenda, KPIs, responsables y actas. | G9: La revisión conecta desviaciones con acciones, forecast, responsables e impacto esperado. | H9: Performance management continuo, integrado con decisiones de negocio, incentivos y mejora predictiva. | L9: =IF(COUNTA(I9:K9)=0,"",ROUND(AVERAGE(I9:K9),2)) | M9: =IF(L9="","",IF(L9<1.5,"1 - Inicial",IF(L9<2.5,"2 - Estructurado",IF(L9<3.5,"3 - Estandarizado",IF(L9<4.5,"4 - Optimizado","5 - Avanzado/Referente"))))) | N9: =IF(L9="","",MAX(0,4-L9)) | O9: =IF(L9="","",IF(N9>=2,"Alta",IF(N9>=1,"Media","Baja"))) | P9: ¿Existen comités de performance? ¿Se documentan decisiones? ¿Se asignan owners? ¿Se mide impacto de acciones? | Q9: Calendario de comités; actas; trackers de acciones; KPIs de impacto; reportes de seguimiento. | R9: Formalizar rutinas de revisión del rendimiento con agenda estándar, registro de acciones, responsables, beneficios esperados y seguimiento.
A10: Evaluación business case | B10: 3.1 Metodología de business case | C10: Evaluar si existen criterios homogéneos para construir, revisar y aprobar business cases. | D10: Business cases ad hoc, con estructura, supuestos y métricas variables. | E10: Plantillas parciales para iniciativas relevantes, con criterios financieros básicos. | F10: Metodología común con inversión, costes, beneficios, riesgos, supuestos y métricas financieras. | G10: Metodología integrada con escenarios, sensibilidad, dependencias, beneficios no financieros y gobierno de aprobación. | H10: Gestión de la cartera de iniciativas basada en valor, con priorización dinámica, seguimiento de beneficios y aprendizaje posterior a la implantación. | L10: =IF(COUNTA(I10:K10)=0,"",ROUND(AVERAGE(I10:K10),2)) | M10: =IF(L10="","",IF(L10<1.5,"1 - Inicial",IF(L10<2.5,"2 - Estructurado",IF(L10<3.5,"3 - Estandarizado",IF(L10<4.5,"4 - Optimizado","5 - Avanzado/Referente"))))) | N10: =IF(L10="","",MAX(0,4-L10)) | O10: =IF(L10="","",IF(N10>=2,"Alta",IF(N10>=1,"Media","Baja"))) | P10: ¿Existe plantilla estándar? ¿Qué métricas se usan? ¿Se documentan supuestos y riesgos? ¿Se revisan beneficios después? | Q10: Plantillas; guías metodológicas; comités de inversión; KPIs ROI/NPV/payback; registros de supuestos. | R10: Diseñar metodología corporativa de business case con plantillas, métricas, supuestos, riesgos, escenarios y gobierno de aprobación.
A11: Evaluación business case | B11: 3.2 Modelización financiera de iniciativas | C11: Evaluar si los business cases incluyen modelos financieros robustos, trazables y comparables. | D11: Modelos manuales no homogéneos y difíciles de comparar entre iniciativas. | E11: Modelos básicos de costes/beneficios, con algunas métricas comunes. | F11: Modelos financieros homogéneos, con supuestos, flujos, inversión, costes, beneficios y sensibilidad básica. | G11: Modelos integrados con escenarios, impactos P&L/cash/balance, riesgos y dependencias. | H11: Modelización avanzada con simulación, probabilización de escenarios y recomendaciones de priorización. | L11: =IF(COUNTA(I11:K11)=0,"",ROUND(AVERAGE(I11:K11),2)) | M11: =IF(L11="","",IF(L11<1.5,"1 - Inicial",IF(L11<2.5,"2 - Estructurado",IF(L11<3.5,"3 - Estandarizado",IF(L11<4.5,"4 - Optimizado","5 - Avanzado/Referente"))))) | N11: =IF(L11="","",MAX(0,4-L11)) | O11: =IF(L11="","",IF(N11>=2,"Alta",IF(N11>=1,"Media","Baja"))) | P11: ¿Los modelos son comparables? ¿Incluyen P&L, cash y balance? ¿Hay sensibilidad? ¿Se documentan supuestos? | Q11: Modelos financieros; bibliotecas de supuestos; análisis de sensibilidad; outputs de comité; documentación metodológica. | R11: Construir modelo financiero estándar para iniciativas con cuenta de resultados, caja, balance, sensibilidad, escenarios y trazabilidad de supuestos.
A12: Evaluación business case | B12: 3.3 Priorización y asignación de capital | C12: Evaluar si los business cases se usan para priorizar iniciativas y asignar recursos de forma objetiva. | D12: Priorización basada en urgencia o criterio cualitativo, sin metodología común. | E12: Se consideran criterios financieros básicos, pero no existe scoring homogéneo. | F12: Matriz común de priorización con valor, esfuerzo, riesgo, alineamiento estratégico y capacidad de ejecución. | G12: Priorización integrada con planificación financiera, portfolio, dependencias y disponibilidad presupuestaria. | H12: Asignación dinámica de capital y recursos basada en valor ajustado por riesgo, escenarios y seguimiento de beneficios. | L12: =IF(COUNTA(I12:K12)=0,"",ROUND(AVERAGE(I12:K12),2)) | M12: =IF(L12="","",IF(L12<1.5,"1 - Inicial",IF(L12<2.5,"2 - Estructurado",IF(L12<3.5,"3 - Estandarizado",IF(L12<4.5,"4 - Optimizado","5 - Avanzado/Referente"))))) | N12: =IF(L12="","",MAX(0,4-L12)) | O12: =IF(L12="","",IF(N12>=2,"Alta",IF(N12>=1,"Media","Baja"))) | P12: ¿Existe scoring de iniciativas? ¿Se prioriza por valor/esfuerzo/riesgo? ¿Se consideran dependencias y capacidad? ¿Se revisa el portfolio periódicamente? | Q12: Matriz de priorización; portfolio de iniciativas; actas de comité; criterios de inversión; roadmap financiero. | R12: Crear modelo de priorización de iniciativas basado en valor, esfuerzo, riesgo, alineamiento, dependencias y capacidad de ejecución.
A13: Evaluación business case | B13: 3.4 Seguimiento de beneficios y post-mortem | C13: Evaluar si los beneficios comprometidos en business cases se monitorizan y se extraen aprendizajes. | D13: No se realiza seguimiento sistemático de beneficios tras aprobación. | E13: Seguimiento parcial de iniciativas relevantes, normalmente financiero y manual. | F13: Tracking periódico de beneficios vs business case, con owners y métricas definidas. | G13: Seguimiento de beneficios integrado con reporting, forecast, acciones correctivas y revisión de supuestos. | H13: Gestión continua de beneficios, con post-mortems, aprendizaje organizativo y recalibración de modelos de decisión. | L13: =IF(COUNTA(I13:K13)=0,"",ROUND(AVERAGE(I13:K13),2)) | M13: =IF(L13="","",IF(L13<1.5,"1 - Inicial",IF(L13<2.5,"2 - Estructurado",IF(L13<3.5,"3 - Estandarizado",IF(L13<4.5,"4 - Optimizado","5 - Avanzado/Referente"))))) | N13: =IF(L13="","",MAX(0,4-L13)) | O13: =IF(L13="","",IF(N13>=2,"Alta",IF(N13>=1,"Media","Baja"))) | P13: ¿Se miden beneficios reales vs estimados? ¿Hay owners de beneficios? ¿Se hacen post-mortems? ¿Los aprendizajes mejoran futuros business cases? | Q13: Benefit tracker; informes post-implementación; actas de revisión; acciones correctivas; repositorio de aprendizajes. | R13: Implantar seguimiento de beneficios con responsables, métricas, línea base, revisiones periódicas y revisión posterior a la implantación.
... A21: Planificación largo plazo | B21: 5.4 Seguimiento de creación de valor a largo plazo | C21: Evaluar si FP&A mide la creación de valor asociada a planes e iniciativas estratégicas a lo largo del tiempo. | D21: No existe seguimiento estructurado de creación de valor a largo plazo. | E21: Se revisan métricas financieras agregadas, pero sin conexión clara con iniciativas estratégicas. | F21: KPIs de valor definidos y seguimiento periódico de avance frente al plan estratégico. | G21: Seguimiento integrado de valor, riesgos, beneficios, cash, rentabilidad e iniciativas, con acciones correctivas. | H21: Gestión activa de creación de valor, con métricas anticipativas, reasignación dinámica de capital y aprendizaje continuo. | L21: =IF(COUNTA(I21:K21)=0,"",ROUND(AVERAGE(I21:K21),2)) | M21: =IF(L21="","",IF(L21<1.5,"1 - Inicial",IF(L21<2.5,"2 - Estructurado",IF(L21<3.5,"3 - Estandarizado",IF(L21<4.5,"4 - Optimizado","5 - Avanzado/Referente"))))) | N21: =IF(L21="","",MAX(0,4-L21)) | O21: =IF(L21="","",IF(N21>=2,"Alta",IF(N21>=1,"Media","Baja"))) | P21: ¿Se mide creación de valor a largo plazo? ¿Se conectan KPIs con iniciativas estratégicas? ¿Se revisan beneficios y riesgos? ¿Se toman acciones de reasignación? | Q21: KPIs de valor; benefit tracking estratégico; reportes de plan; actas de comité; decisiones de reasignación. | R21: Implantar modelo de seguimiento de creación de valor con KPIs, beneficios, riesgos, responsables y revisión periódica de asignación de recursos.

Sheet Resumen
A1: Capacidad | B1: Score Procesos | C1: Score Tecnología | D1: Score Organización | E1: Score Medio | F1: Gap vs objetivo | G1: Prioridad
A2: Presupuestos y previsiones | B2: =IFERROR(ROUND(AVERAGEIF(Assessment!$A:$A,A2,Assessment!$I:$I),2),"") -> 2 | C2: =IFERROR(ROUND(AVERAGEIF(Assessment!$A:$A,A2,Assessment!$J:$J),2),"") -> 4 | D2: =IFERROR(ROUND(AVERAGEIF(Assessment!$A:$A,A2,Assessment!$K:$K),2),"") -> 3 | E2: =IFERROR(ROUND(AVERAGEIF(Assessment!$A:$A,A2,Assessment!$L:$L),2),"") -> 3 | F2: =IF(E2="","",MAX(0,4-E2)) -> 1 | G2: =IF(E2="","",IF(F2>=2,"Alta",IF(F2>=1,"Media","Baja"))) -> Media
A3: Informes de gestión del rendimiento | B3: =IFERROR(ROUND(AVERAGEIF(Assessment!$A:$A,A3,Assessment!$I:$I),2),"") | C3: =IFERROR(ROUND(AVERAGEIF(Assessment!$A:$A,A3,Assessment!$J:$J),2),"") | D3: =IFERROR(ROUND(AVERAGEIF(Assessment!$A:$A,A3,Assessment!$K:$K),2),"") | E3: =IFERROR(ROUND(AVERAGEIF(Assessment!$A:$A,A3,Assessment!$L:$L),2),"") | F3: =IF(E3="","",MAX(0,4-E3)) | G3: =IF(E3="","",IF(F3>=2,"Alta",IF(F3>=1,"Media","Baja")))
A4: Evaluación business case | B4: =IFERROR(ROUND(AVERAGEIF(Assessment!$A:$A,A4,Assessment!$I:$I),2),"") | C4: =IFERROR(ROUND(AVERAGEIF(Assessment!$A:$A,A4,Assessment!$J:$J),2),"") | D4: =IFERROR(ROUND(AVERAGEIF(Assessment!$A:$A,A4,Assessment!$K:$K),2),"") | E4: =IFERROR(ROUND(AVERAGEIF(Assessment!$A:$A,A4,Assessment!$L:$L),2),"") | F4: =IF(E4="","",MAX(0,4-E4)) | G4: =IF(E4="","",IF(F4>=2,"Alta",IF(F4>=1,"Media","Baja")))
A5: Información y apoyo a la toma de decisiones | B5: =IFERROR(ROUND(AVERAGEIF(Assessment!$A:$A,A5,Assessment!$I:$I),2),"") | C5: =IFERROR(ROUND(AVERAGEIF(Assessment!$A:$A,A5,Assessment!$J:$J),2),"") | D5: =IFERROR(ROUND(AVERAGEIF(Assessment!$A:$A,A5,Assessment!$K:$K),2),"") | E5: =IFERROR(ROUND(AVERAGEIF(Assessment!$A:$A,A5,Assessment!$L:$L),2),"") | F5: =IF(E5="","",MAX(0,4-E5)) | G5: =IF(E5="","",IF(F5>=2,"Alta",IF(F5>=1,"Media","Baja")))
A6: Planificación largo plazo | B6: =IFERROR(ROUND(AVERAGEIF(Assessment!$A:$A,A6,Assessment!$I:$I),2),"") | C6: =IFERROR(ROUND(AVERAGEIF(Assessment!$A:$A,A6,Assessment!$J:$J),2),"") | D6: =IFERROR(ROUND(AVERAGEIF(Assessment!$A:$A,A6,Assessment!$K:$K),2),"") | E6: =IFERROR(ROUND(AVERAGEIF(Assessment!$A:$A,A6,Assessment!$L:$L),2),"") | F6: =IF(E6="","",MAX(0,4-E6)) | G6: =IF(E6="","",IF(F6>=2,"Alta",IF(F6>=1,"Media","Baja")))
A8: Score global dominio | B8: =IFERROR(ROUND(AVERAGE(B2:B6),2),"") -> 2 | C8: =IFERROR(ROUND(AVERAGE(C2:C6),2),"") -> 4 | D8: =IFERROR(ROUND(AVERAGE(D2:D6),2),"") -> 3 | E8: =IFERROR(ROUND(AVERAGE(E2:E6),2),"") -> 3 | F8: =IFERROR(ROUND(AVERAGE(F2:F6),2),"") -> 1 | G8: =IF(E8="","",IF(F8>=2,"Alta",IF(F8>=1,"Media","Baja"))) -> Media

Sheet Heatmap
A1: Capacidad | B1: Subcapacidad | C1: Procesos | D1: Tecnología | E1: Organización | F1: Score medio | G1: Gap | H1: Prioridad
A2: =Assessment!A2 -> Presupuestos y previsiones | B2: =Assessment!B2 -> 1.1 Gobierno del proceso presupuestario y forecast | C2: =Assessment!I2 -> 2 | D2: =Assessment!J2 -> 4 | E2: =Assessment!K2 -> 3 | F2: =Assessment!L2 -> 3 | G2: =Assessment!N2 -> 1 | H2: =Assessment!O2 -> Media
A3: =Assessment!A3 -> Presupuestos y previsiones | B3: =Assessment!B3 -> 1.2 Modelo presupuestario y drivers de planificación | C3: =Assessment!I3 -> 0 | D3: =Assessment!J3 -> 0 | E3: =Assessment!K3 -> 0 | F3: =Assessment!L3 | G3: =Assessment!N3 | H3: =Assessment!O3
A4: =Assessment!A4 -> Presupuestos y previsiones | B4: =Assessment!B4 -> 1.3 Integración de escenarios y rolling forecast | C4: =Assessment!I4 -> 0 | D4: =Assessment!J4 -> 0 | E4: =Assessment!K4 -> 0 | F4: =Assessment!L4 | G4: =Assessment!N4 | H4: =Assessment!O4
A5: =Assessment!A5 -> Presupuestos y previsiones | B5: =Assessment!B5 -> 1.4 Colaboración y accountability presupuestaria | C5: =Assessment!I5 -> 0 | D5: =Assessment!J5 -> 0 | E5: =Assessment!K5 -> 0 | F5: =Assessment!L5 | G5: =Assessment!N5 | H5: =Assessment!O5
A6: =Assessment!A6 -> Informes de gestión del rendimiento | B6: =Assessment!B6 -> 2.1 Modelo de reporting de performance | C6: =Assessment!I6 -> 0 | D6: =Assessment!J6 -> 0 | E6: =Assessment!K6 -> 0 | F6: =Assessment!L6 | G6: =Assessment!N6 | H6: =Assessment!O6
A7: =Assessment!A7 -> Informes de gestión del rendimiento | B7: =Assessment!B7 -> 2.2 Análisis de desviaciones y causa-raíz | C7: =Assessment!I7 -> 0 | D7: =Assessment!J7 -> 0 | E7: =Assessment!K7 -> 0 | F7: =Assessment!L7 | G7: =Assessment!N7 | H7: =Assessment!O7
A8: =Assessment!A8 -> Informes de gestión del rendimiento | B8: =Assessment!B8 -> 2.3 Cuadros de mando y visualización ejecutiva | C8: =Assessment!I8 -> 0 | D8: =Assessment!J8 -> 0 | E8: =Assessment!K8 -> 0 | F8: =Assessment!L8 | G8: =Assessment!N8 | H8: =Assessment!O8
A9: =Assessment!A9 -> Informes de gestión del rendimiento | B9: =Assessment!B9 -> 2.4 Rutinas de performance y toma de acciones | C9: =Assessment!I9 -> 0 | D9: =Assessment!J9 -> 0 | E9: =Assessment!K9 -> 0 | F9: =Assessment!L9 | G9: =Assessment!N9 | H9: =Assessment!O9
A10: =Assessment!A10 -> Evaluación business case | B10: =Assessment!B10 -> 3.1 Metodología de business case | C10: =Assessment!I10 -> 0 | D10: =Assessment!J10 -> 0 | E10: =Assessment!K10 -> 0 | F10: =Assessment!L10 | G10: =Assessment!N10 | H10: =Assessment!O10
A11: =Assessment!A11 -> Evaluación business case | B11: =Assessment!B11 -> 3.2 Modelización financiera de iniciativas | C11: =Assessment!I11 -> 0 | D11: =Assessment!J11 -> 0 | E11: =Assessment!K11 -> 0 | F11: =Assessment!L11 | G11: =Assessment!N11 | H11: =Assessment!O11
A12: =Assessment!A12 -> Evaluación business case | B12: =Assessment!B12 -> 3.3 Priorización y asignación de capital | C12: =Assessment!I12 -> 0 | D12: =Assessment!J12 -> 0 | E12: =Assessment!K12 -> 0 | F12: =Assessment!L12 | G12: =Assessment!N12 | H12: =Assessment!O12
A13: =Assessment!A13 -> Evaluación business case | B13: =Assessment!B13 -> 3.4 Seguimiento de beneficios y post-mortem | C13: =Assessment!I13 -> 0 | D13: =Assessment!J13 -> 0 | E13: =Assessment!K13 -> 0 | F13: =Assessment!L13 | G13: =Assessment!N13 | H13: =Assessment!O13
... A21: =Assessment!A21 -> Planificación largo plazo | B21: =Assessment!B21 -> 5.4 Seguimiento de creación de valor a largo plazo | C21: =Assessment!I21 -> 0 | D21: =Assessment!J21 -> 0 | E21: =Assessment!K21 -> 0 | F21: =Assessment!L21 | G21: =Assessment!N21 | H21: =Assessment!O21

Sheet Roadmap
A1: Capacidad | B1: Subcapacidad | C1: Gap | D1: Prioridad | E1: Iniciativa sugerida | F1: Oleada | G1: Owner | H1: Estado | I1: Comentarios
A2: =Assessment!A2 -> Presupuestos y previsiones | B2: =Assessment!B2 -> 1.1 Gobierno del proceso presupuestario y forecast | C2: =Assessment!N2 -> 1 | D2: =Assessment!O2 -> Media | E2: =Assessment!R2 -> Diseñar modelo de gobierno FP&A con calendario integrado, RACI, flujo de aprobación, criterios comunes y control de versiones. | F2: =IF(D2="Alta","Oleada 1",IF(D2="Media","Oleada 2","Oleada 3")) -> Oleada 2 | H2: No iniciado
A3: =Assessment!A3 -> Presupuestos y previsiones | B3: =Assessment!B3 -> 1.2 Modelo presupuestario y drivers de planificación | C3: =Assessment!N3 | D3: =Assessment!O3 | E3: =Assessment!R3 -> Evolucionar hacia una planificación basada en drivers, con catálogo de drivers, reglas de cálculo, trazabilidad y análisis de sensibilidad. | F3: =IF(D3="Alta","Oleada 1",IF(D3="Media","Oleada 2","Oleada 3")) -> Oleada 3 | H3: No iniciado
A4: =Assessment!A4 -> Presupuestos y previsiones | B4: =Assessment!B4 -> 1.3 Integración de escenarios y rolling forecast | C4: =Assessment!N4 | D4: =Assessment!O4 | E4: =Assessment!R4 -> Implantar previsión continua (rolling forecast) con escenarios base, optimista y pesimista, supuestos documentados y automatización de los datos de entrada críticos. | F4: =IF(D4="Alta","Oleada 1",IF(D4="Media","Oleada 2","Oleada 3")) -> Oleada 3 | H4: No iniciado
A5: =Assessment!A5 -> Presupuestos y previsiones | B5: =Assessment!B5 -> 1.4 Colaboración y accountability presupuestaria | C5: =Assessment!N5 | D5: =Assessment!O5 | E5: =Assessment!R5 -> Definir la responsabilidad presupuestaria por dimensión y unidad, con flujo colaborativo, contraste financiero y seguimiento de compromisos. | F5: =IF(D5="Alta","Oleada 1",IF(D5="Media","Oleada 2","Oleada 3")) -> Oleada 3 | H5: No iniciado
A6: =Assessment!A6 -> Informes de gestión del rendimiento | B6: =Assessment!B6 -> 2.1 Modelo de reporting de performance | C6: =Assessment!N6 | D6: =Assessment!O6 | E6: =Assessment!R6 -> Rediseñar los informes de gestión alrededor de objetivos, KPIs, desviaciones, causas, responsables y acciones. | F6: =IF(D6="Alta","Oleada 1",IF(D6="Media","Oleada 2","Oleada 3")) -> Oleada 3 | H6: No iniciado
A7: =Assessment!A7 -> Informes de gestión del rendimiento | B7: =Assessment!B7 -> 2.2 Análisis de desviaciones y causa-raíz | C7: =Assessment!N7 | D7: =Assessment!O7 | E7: =Assessment!R7 -> Crear metodología de análisis de desviaciones por driver, dimensión, responsable, causa-raíz, acción y seguimiento. | F7: =IF(D7="Alta","Oleada 1",IF(D7="Media","Oleada 2","Oleada 3")) -> Oleada 3 | H7: No iniciado
A8: =Assessment!A8 -> Informes de gestión del rendimiento | B8: =Assessment!B8 -> 2.3 Cuadros de mando y visualización ejecutiva | C8: =Assessment!N8 | D8: =Assessment!O8 | E8: =Assessment!R8 -> Implantar cuadro de mando FP&A con KPIs homologados, navegación al detalle, acceso por perfil y automatización de datos. | F8: =IF(D8="Alta","Oleada 1",IF(D8="Media","Oleada 2","Oleada 3")) -> Oleada 3 | H8: No iniciado
A9: =Assessment!A9 -> Informes de gestión del rendimiento | B9: =Assessment!B9 -> 2.4 Rutinas de performance y toma de acciones | C9: =Assessment!N9 | D9: =Assessment!O9 | E9: =Assessment!R9 -> Formalizar rutinas de revisión del rendimiento con agenda estándar, registro de acciones, responsables, beneficios esperados y seguimiento. | F9: =IF(D9="Alta","Oleada 1",IF(D9="Media","Oleada 2","Oleada 3")) -> Oleada 3 | H9: No iniciado
A10: =Assessment!A10 -> Evaluación business case | B10: =Assessment!B10 -> 3.1 Metodología de business case | C10: =Assessment!N10 | D10: =Assessment!O10 | E10: =Assessment!R10 -> Diseñar metodología corporativa de business case con plantillas, métricas, supuestos, riesgos, escenarios y gobierno de aprobación. | F10: =IF(D10="Alta","Oleada 1",IF(D10="Media","Oleada 2","Oleada 3")) -> Oleada 3 | H10: No iniciado
A11: =Assessment!A11 -> Evaluación business case | B11: =Assessment!B11 -> 3.2 Modelización financiera de iniciativas | C11: =Assessment!N11 | D11: =Assessment!O11 | E11: =Assessment!R11 -> Construir modelo financiero estándar para iniciativas con cuenta de resultados, caja, balance, sensibilidad, escenarios y trazabilidad de supuestos. | F11: =IF(D11="Alta","Oleada 1",IF(D11="Media","Oleada 2","Oleada 3")) -> Oleada 3 | H11: No iniciado
A12: =Assessment!A12 -> Evaluación business case | B12: =Assessment!B12 -> 3.3 Priorización y asignación de capital | C12: =Assessment!N12 | D12: =Assessment!O12 | E12: =Assessment!R12 -> Crear modelo de priorización de iniciativas basado en valor, esfuerzo, riesgo, alineamiento, dependencias y capacidad de ejecución. | F12: =IF(D12="Alta","Oleada 1",IF(D12="Media","Oleada 2","Oleada 3")) -> Oleada 3 | H12: No iniciado
A13: =Assessment!A13 -> Evaluación business case | B13: =Assessment!B13 -> 3.4 Seguimiento de beneficios y post-mortem | C13: =Assessment!N13 | D13: =Assessment!O13 | E13: =Assessment!R13 -> Implantar seguimiento de beneficios con responsables, métricas, línea base, revisiones periódicas y revisión posterior a la implantación. | F13: =IF(D13="Alta","Oleada 1",IF(D13="Media","Oleada 2","Oleada 3")) -> Oleada 3 | H13: No iniciado
... A21: =Assessment!A21 -> Planificación largo plazo | B21: =Assessment!B21 -> 5.4 Seguimiento de creación de valor a largo plazo | C21: =Assessment!N21 | D21: =Assessment!O21 | E21: =Assessment!R21 -> Implantar modelo de seguimiento de creación de valor con KPIs, beneficios, riesgos, responsables y revisión periódica de asignación de recursos. | F21: =IF(D21="Alta","Oleada 1",IF(D21="Media","Oleada 2","Oleada 3")) -> Oleada 3 | H21: No iniciado

Sheet Instrucciones
A1: F3M - FP&A | Assessment-ready
A2: Uso del fichero
A3: 1. En 'Assessment', puntuar cada subcapacidad en las tres palancas: Procesos, Tecnología y Organización.
A4: 2. Utilizar valores enteros de 1 a 5, donde 1 = Inicial y 5 = Avanzado/Referente.
A5: 3. El Score Medio, Nivel resultante, Gap y Prioridad se calculan automáticamente.
A6: 4. Objetivo de madurez utilizado para el gap: Nivel 4 - Optimizado.
A7: 5. 'Resumen' consolida resultados por capacidad y gráfico ejecutivo.
A8: 6. 'Heatmap' facilita la lectura visual por subcapacidad y palanca.
A9: 7. 'Roadmap' convierte gaps en iniciativas sugeridas y oleadas.
A10: Escala F3M
A11: 1 - Inicial: modelo básico, operativo, heterogéneo y poco formalizado.
A12: 2 - Estructurado: prácticas definidas, con consistencia parcial y dependencias manuales.
... A15: 5 - Avanzado/Referente: modelo maduro, estratégico, anticipativo y orientado a generación de valor.

Sheet Guias scoring
A1: GUÍAS DE SCORING F3M
A3: PROCESOS
A4: Nivel 1 - Inicial: No existe proceso formal o es ad hoc
A5: Nivel 2 - Estructurado: Proceso parcial o inconsistente
A6: Nivel 3 - Estandarizado: Proceso homogéneo y documentado
A7: Nivel 4 - Optimizado: Proceso medido y eficiente
A8: Nivel 5 - Avanzado: Proceso integrado y orientado a decisiones
A9: Checklist:
A10: - Existe proceso formal
A11: - Es consistente
A12: - Está medido
A13: - Impacta decisiones
... A51: ¿Existen capacidades predictivas o AI en producción?

Sheet AI Overlay
A1: Capacidad | B1: Subcapacidad | C1: Casos de uso AI asociados | D1: Aplicación en nivel avanzado | E1: Fuente
A2: Presupuestos y previsiones | B2: 1.1 Gobierno del proceso presupuestario y forecast | C2: Flujos guiados de elaboración presupuestaria; Previsión y escenarios bajo demanda | D2: IA guía el calendario presupuestario, detecta retrasos y dependencias entre áreas y propone la replanificación cuando cambian los supuestos. | E2: F3M_AI_Mapping_Consolidado_v1.xlsx
A3: Presupuestos y previsiones | B3: 1.2 Modelo presupuestario y drivers de planificación | C3: Flujos guiados de elaboración presupuestaria; Asignación presupuestaria asistida por IA; Patrones históricos para predecir el rendimiento | D3: IA identifica los drivers que mejor explican el resultado, propone sus valores de partida y cuantifica la sensibilidad de cada uno. | E3: F3M_AI_Mapping_Consolidado_v1.xlsx
A4: Presupuestos y previsiones | B4: 1.3 Integración de escenarios y rolling forecast | C4: Previsión y escenarios bajo demanda; Patrones históricos para predecir el rendimiento | D4: IA genera el forecast de forma continua, construye escenarios alternativos bajo demanda y alerta cuando la desviación esperada supera el umbral. | E4: F3M_AI_Mapping_Consolidado_v1.xlsx
A5: Presupuestos y previsiones | B5: 1.4 Colaboración y accountability presupuestaria | C5: Flujos guiados de elaboración presupuestaria; Analista digital de Finanzas bajo demanda | D5: IA guía la aportación de cada responsable, valida su coherencia con los drivers acordados y da seguimiento a los compromisos adquiridos. | E5: F3M_AI_Mapping_Consolidado_v1.xlsx
A6: Informes de gestión del rendimiento | B6: 2.1 Modelo de reporting de performance | C6: Informes de gestión con comentario automático; Analista digital de Finanzas bajo demanda | D6: IA produce el informe de gestión con la desviación calculada y el comentario redactado, y ajusta el nivel de detalle a cada destinatario. | E6: F3M_AI_Mapping_Consolidado_v1.xlsx
A7: Informes de gestión del rendimiento | B7: 2.2 Análisis de desviaciones y causa-raíz | C7: Análisis de desviaciones con explicación automática; Patrones históricos para predecir el rendimiento | D7: IA descompone la desviación por driver, identifica la causa raíz y anticipa si la brecha se va a cerrar o a ampliar. | E7: F3M_AI_Mapping_Consolidado_v1.xlsx
A8: Informes de gestión del rendimiento | B8: 2.3 Cuadros de mando y visualización ejecutiva | C8: Analista digital de Finanzas bajo demanda; Consulta del dato en lenguaje natural | D8: IA acompaña el cuadro de mando con conclusiones automáticas, alertas y respuesta a preguntas en lenguaje natural sobre el propio dato. | E8: F3M_AI_Mapping_Consolidado_v1.xlsx
A9: Informes de gestión del rendimiento | B9: 2.4 Rutinas de performance y toma de acciones | C9: Informes de gestión con comentario automático; Recomendaciones de acción a nivel de proyecto; Reporting estandarizado de revisión de desempeño | D9: IA prepara la reunión de seguimiento con las desviaciones relevantes, las acciones pendientes y una recomendación priorizada para cada una. | E9: F3M_AI_Mapping_Consolidado_v1.xlsx
A10: Evaluación business case | B10: 3.1 Metodología de business case | C10: Resumen y puntuación de propuestas de inversión; Recomendaciones de acción a nivel de proyecto | D10: IA revisa que cada business case cumpla la plantilla corporativa, resume su propuesta y señala los supuestos que quedan sin justificar. | E10: F3M_AI_Mapping_Consolidado_v1.xlsx
A11: Evaluación business case | B11: 3.2 Modelización financiera de iniciativas | C11: Previsión y escenarios bajo demanda; Resumen y puntuación de propuestas de inversión | D11: IA construye los escenarios del business case, prueba la sensibilidad de los supuestos y compara el modelo con iniciativas anteriores comparables. | E11: F3M_AI_Mapping_Consolidado_v1.xlsx
A12: Evaluación business case | B12: 3.3 Priorización y asignación de capital | C12: Resumen y puntuación de propuestas de inversión; Asignación presupuestaria asistida por IA | D12: IA puntúa y ordena la cartera de iniciativas por valor ajustado a riesgo y propone cómo repartir el capital disponible entre ellas. | E12: F3M_AI_Mapping_Consolidado_v1.xlsx
... A21: Planificación largo plazo | B21: 5.4 Seguimiento de creación de valor a largo plazo | C21: Patrones históricos para predecir el rendimiento; Generación de estrategias de inversión | D21: IA mide la creación de valor de cada plan, la anticipa con indicadores adelantados y recomienda reasignar capital antes de que se deteriore. | E21: F3M_AI_Mapping_Consolidado_v1.xlsx
